{"global_pose":{"position":{"x":0.0,"y":0.030000003192748887,"z":0.0},"rotation":{"w":1.0000000532124802,"x":0.0,"y":0.0,"z":0.0}},"ir_pose":{"position":{"x":0.10000001064249633,"y":0.030000003192748887,"z":0.0},"rotation":{"w":0.7071068376269066,"x":0.0,"y":0.0,"z":-0.7071068376269066}},"left_encoder_data_input":{"revolutions_per_second":0.0,"step_position":0},"line_following_statistics":{"average_speed":0.0,"time_spent_on_line":0.0,"tracking_error":0.0},"right_encoder_data_input":{"revolutions_per_second":0.0,"step_position":0},"timestamp":{"system_time_us":0}}
{"global_pose":{"position":{"x":0.0,"y":0.030000003192748887,"z":0.0},"rotation":{"w":1.0000000532124802,"x":0.0,"y":0.0,"z":0.0}},"ir_pose":{"position":{"x":0.10000001064249633,"y":0.030000003192748887,"z":0.0},"rotation":{"w":0.7071068376269066,"x":0.0,"y":0.0,"z":-0.7071068376269066}},"left_encoder_data_input":{"revolutions_per_second":10.0,"step_position":2},"line_following_statistics":{"average_speed":10.0,"time_spent_on_line":0.0,"tracking_error":0.9285714285714286},"right_encoder_data_input":{"revolutions_per_second":10.0,"step_position":2},"timestamp":{"system_time_us":838266503}}
{"global_pose":{"position":{"x":0.006233548806656421,"y":0.030000003192748884,"z":0.0},"rotation":{"w":1.0000000532124802,"x":0.0,"y":0.0,"z":0.0}},"ir_pose":{"position":{"x":0.10623355944915275,"y":0.030000003192748884,"z":0.0},"rotation":{"w":0.7071068376269066,"x":0.0,"y":0.0,"z":-0.7071068376269066}},"left_encoder_data_input":{"revolutions_per_second":10.0,"step_position":5},"line_following_statistics":{"average_speed":10.0,"time_spent_on_line":0.009991,"tracking_error":0.9285714285714286},"right_encoder_data_input":{"revolutions_per_second":10.0,"step_position":4},"timestamp":{"system_time_us":838276494}}
{"global_pose":{"position":{"x":0.012443221506604554,"y":0.030000003192748884,"z":0.0},"rotation":{"w":1.0000000532124802,"x":0.0,"y":0.0,"z":0.0}},"ir_pose":{"position":{"x":0.11244323214910089,"y":0.030000003192748884,"z":0.0},"rotation":{"w":0.7071068376269066,"x":0.0,"y":0.0,"z":-0.7071068376269066}},"left_encoder_data_input":{"revolutions_per_second":101.41419602786351,"step_position":30},"line_following_statistics":{"average_speed":101.41419602786351,"time_spent_on_line":0.019993999999999998,"tracking_error":0.9285714285714286},"right_encoder_data_input":{"revolutions_per_second":101.41419602786351,"step_position":30},"timestamp":{"system_time_us":838286497}}
{"global_pose":{"position":{"x":0.07587053297325337,"y":0.030000003192748884,"z":0.0},"rotation":{"w":1.0000000532124802,"x":0.0,"y":0.0,"z":0.0}},"ir_pose":{"position":{"x":0.17587054361574972,"y":0.030000003192748884,"z":0.0},"rotation":{"w":0.7071068376269066,"x":0.0,"y":0.0,"z":-0.7071068376269066}},"left_encoder_data_input":{"revolutions_per_second":0.02238866403401865,"step_position":30},"line_following_statistics":{"average_speed":0.02238866403401865,"time_spent_on_line":0.029997999999999997,"tracking_error":0.9285714285714286},"right_encoder_data_input":{"revolutions_per_second":0.02238866403401865,"step_position":30},"timestamp":{"system_time_us":838296501}}
{"global_pose":{"position":{"x":0.07588563834763334,"y":0.030000003192748884,"z":0.0},"rotation":{"w":1.0000000532124802,"x":0.0,"y":0.0,"z":0.0}},"ir_pose":{"position":{"x":0.17588564899012968,"y":0.030000003192748884,"z":0.0},"rotation":{"w":0.7071068376269066,"x":0.0,"y":0.0,"z":-0.7071068376269066}},"left_encoder_data_input":{"revolutions_per_second":101.41419602786351,"step_position":55},"line_following_statistics":{"average_speed":101.41419602786351,"time_spent_on_line":0.039996,"tracking_error":0.9285714285714286},"right_encoder_data_input":{"revolutions_per_second":101.41419602786351,"step_position":55},"timestamp":{"system_time_us":838306499}}
{"global_pose":{"position":{"x":0.13496084475785045,"y":0.03000000319274889,"z":0.0},"rotation":{"w":1.0000000532124802,"x":0.0,"y":0.0,"z":0.0}},"ir_pose":{"position":{"x":0.23496085540034678,"y":0.03000000319274889,"z":0.0},"rotation":{"w":0.7071068376269066,"x":0.0,"y":0.0,"z":-0.7071068376269066}},"left_encoder_data_input":{"revolutions_per_second":0.02238866403401865,"step_position":55},"line_following_statistics":{"average_speed":0.02238866403401865,"time_spent_on_line":0.049996,"tracking_error":0.9285714285714286},"right_encoder_data_input":{"revolutions_per_second":0.02238866403401865,"step_position":55},"timestamp":{"system_time_us":838316499}}
{"global_pose":{"position":{"x":0.1349749780877439,"y":0.030000003192748877,"z":0.0},"rotation":{"w":1.0000000532124802,"x":0.0,"y":0.0,"z":0.0}},"ir_pose":{"position":{"x":0.23497498873024023,"y":0.030000003192748877,"z":0.0},"rotation":{"w":0.7071068376269066,"x":0.0,"y":0.0,"z":-0.7071068376269066}},"left_encoder_data_input":{"revolutions_per_second":101.41419602786351,"step_position":81},"line_following_statistics":{"average_speed":101.41419602786351,"time_spent_on_line":0.059995,"tracking_error":0.9285714285714286},"right_encoder_data_input":{"revolutions_per_second":101.41419602786351,"step_position":81},"timestamp":{"system_time_us":838326498}}
{"global_pose":{"position":{"x":0.2087504866431849,"y":0.030000003192748884,"z":0.0},"rotation":{"w":1.0000000532124802,"x":0.0,"y":0.0,"z":0.0}},"ir_pose":{"position":{"x":0.30875049728568127,"y":0.030000003192748884,"z":0.0},"rotation":{"w":0.7071068376269066,"x":0.0,"y":0.0,"z":-0.7071068376269066}},"left_encoder_data_input":{"revolutions_per_second":0.02238866403401865,"step_position":81},"line_following_statistics":{"average_speed":0.02238866403401865,"time_spent_on_line":0.070001,"tracking_error":0.9285714285714286},"right_encoder_data_input":{"revolutions_per_second":0.02238866403401865,"step_position":81},"timestamp":{"system_time_us":838336504}}
{"global_pose":{"position":{"x":0.2087624437750744,"y":0.030000003192748884,"z":0.0},"rotation":{"w":1.0000000532124802,"x":0.0,"y":0.0,"z":0.0}},"ir_pose":{"position":{"x":0.3087624544175708,"y":0.030000003192748884,"z":0.0},"rotation":{"w":0.7071068376269066,"x":0.0,"y":0.0,"z":-0.7071068376269066}},"left_encoder_data_input":{"revolutions_per_second":101.41419602786351,"step_position":106},"line_following_statistics":{"average_speed":101.41419602786351,"time_spent_on_line":0.08000299999999999,"tracking_error":0.9285714285714286},"right_encoder_data_input":{"revolutions_per_second":101.41419602786351,"step_position":106},"timestamp":{"system_time_us":838346506}}
{"global_pose":{"position":{"x":0.27322202613358554,"y":0.030000003192748884,"z":0.0},"rotation":{"w":1.0000000532124802,"x":0.0,"y":0.0,"z":0.0}},"ir_pose":{"position":{"x":0.3732220367760819,"y":0.030000003192748884,"z":0.0},"rotation":{"w":0.7071068376269066,"x":0.0,"y":0.0,"z":-0.7071068376269066}},"left_encoder_data_input":{"revolutions_per_second":0.02238866403401865,"step_position":106},"line_following_statistics":{"average_speed":0.02238866403401865,"time_spent_on_line":0.09000199999999998,"tracking_error":0.9285714285714286},"right_encoder_data_input":{"revolutions_per_second":0.02238866403401865,"step_position":106},"timestamp":{"system_time_us":838356505}}
{"global_pose":{"position":{"x":0.2732359512687119,"y":0.030000003192748897,"z":0.0},"rotation":{"w":1.0000000532124802,"x":0.0,"y":0.0,"z":0.0}},"ir_pose":{"position":{"x":0.3732359619112082,"y":0.030000003192748897,"z":0.0},"rotation":{"w":0.7071068376269066,"x":0.0,"y":0.0,"z":-0.7071068376269066}},"left_encoder_data_input":{"revolutions_per_second":101.41419602786351,"step_position":131},"line_following_statistics":{"average_speed":101.41419602786351,"time_spent_on_line":0.10000499999999998,"tracking_error":0.9285714285714286},"right_encoder_data_input":{"revolutions_per_second":101.41419602786351,"step_position":131},"timestamp":{"system_time_us":838366508}}
{"global_pose":{"position":{"x":0.3367715874585808,"y":0.03000000319274887,"z":0.0},"rotation":{"w":1.0000000532124802,"x":0.0,"y":0.0,"z":0.0}},"ir_pose":{"position":{"x":0.43677159810107713,"y":0.03000000319274887,"z":0.0},"rotation":{"w":0.7071068376269066,"x":0.0,"y":0.0,"z":-0.7071068376269066}},"left_encoder_data_input":{"revolutions_per_second":0.02238866403401865,"step_position":131},"line_following_statistics":{"average_speed":0.02238866403401865,"time_spent_on_line":0.11000499999999998,"tracking_error":0.9285714285714286},"right_encoder_data_input":{"revolutions_per_second":0.02238866403401865,"step_position":131},"timestamp":{"system_time_us":838376508}}
{"global_pose":{"position":{"x":0.33678601619996806,"y":0.030000003192748897,"z":0.0},"rotation":{"w":1.0000000532124802,"x":0.0,"y":0.0,"z":0.0}},"ir_pose":{"position":{"x":0.43678602684246437,"y":0.030000003192748897,"z":0.0},"rotation":{"w":0.7071068376269066,"x":0.0,"y":0.0,"z":-0.7071068376269066}},"left_encoder_data_input":{"revolutions_per_second":101.41419602786351,"step_position":157},"line_following_statistics":{"average_speed":101.41419602786351,"time_spent_on_line":0.12000599999999997,"tracking_error":0.9285714285714286},"right_encoder_data_input":{"revolutions_per_second":101.41419602786351,"step_position":157},"timestamp":{"system_time_us":838386509}}
{"global_pose":{"position":{"x":0.3990599879664497,"y":0.030000003192748897,"z":0.0},"rotation":{"w":1.0000000532124802,"x":0.0,"y":0.0,"z":0.0}},"ir_pose":{"position":{"x":0.499059998608946,"y":0.030000003192748897,"z":0.0},"rotation":{"w":0.7071068376269066,"x":0.0,"y":0.0,"z":-0.7071068376269066}},"left_encoder_data_input":{"revolutions_per_second":0.02238866403401865,"step_position":157},"line_following_statistics":{"average_speed":0.02238866403401865,"time_spent_on_line":0.13000399999999998,"tracking_error":0.9285714285714286},"right_encoder_data_input":{"revolutions_per_second":0.02238866403401865,"step_position":157},"timestamp":{"system_time_us":838396507}}
{"global_pose":{"position":{"x":0.3990740340796165,"y":0.030000003192748897,"z":0.0},"rotation":{"w":1.0000000532124802,"x":0.0,"y":0.0,"z":0.0}},"ir_pose":{"position":{"x":0.4990740447221128,"y":0.030000003192748897,"z":0.0},"rotation":{"w":0.7071068376269066,"x":0.0,"y":0.0,"z":-0.7071068376269066}},"left_encoder_data_input":{"revolutions_per_second":101.41419602786351,"step_position":182},"line_following_statistics":{"average_speed":101.41419602786351,"time_spent_on_line":0.140006,"tracking_error":0.9285714285714286},"right_encoder_data_input":{"revolutions_per_second":101.41419602786351,"step_position":182},"timestamp":{"system_time_us":838406509}}
{"global_pose":{"position":{"x":0.46278171541812907,"y":0.030000003192748897,"z":0.0},"rotation":{"w":1.0000000532124802,"x":0.0,"y":0.0,"z":0.0}},"ir_pose":{"position":{"x":0.5627817260606254,"y":0.030000003192748897,"z":0.0},"rotation":{"w":0.7071068376269066,"x":0.0,"y":0.0,"z":-0.7071068376269066}},"left_encoder_data_input":{"revolutions_per_second":0.02238866403401865,"step_position":182},"line_following_statistics":{"average_speed":0.02238866403401865,"time_spent_on_line":0.150007,"tracking_error":0.9285714285714286},"right_encoder_data_input":{"revolutions_per_second":0.02238866403401865,"step_position":182},"timestamp":{"system_time_us":838416510}}
{"global_pose":{"position":{"x":0.4627957966993308,"y":0.030000003192748897,"z":0.0},"rotation":{"w":1.0000000532124802,"x":0.0,"y":0.0,"z":0.0}},"ir_pose":{"position":{"x":0.5627958073418271,"y":0.030000003192748897,"z":0.0},"rotation":{"w":0.7071068376269066,"x":0.0,"y":0.0,"z":-0.7071068376269066}},"left_encoder_data_input":{"revolutions_per_second":101.41419602786351,"step_position":207},"line_following_statistics":{"average_speed":101.41419602786351,"time_spent_on_line":0.160005,"tracking_error":0.9285714285714286},"right_encoder_data_input":{"revolutions_per_second":101.41419602786351,"step_position":207},"timestamp":{"system_time_us":838426508}}
{"global_pose":{"position":{"x":0.5262549683786913,"y":0.03000000319274887,"z":0.0},"rotation":{"w":1.0000000532124802,"x":0.0,"y":0.0,"z":0.0}},"ir_pose":{"position":{"x":0.6262549790211877,"y":0.03000000319274887,"z":0.0},"rotation":{"w":0.7071068376269066,"x":0.0,"y":0.0,"z":-0.7071068376269066}},"left_encoder_data_input":{"revolutions_per_second":0.02238866403401865,"step_position":207},"line_following_statistics":{"average_speed":0.02238866403401865,"time_spent_on_line":0.17000900000000002,"tracking_error":0.9285714285714286},"right_encoder_data_input":{"revolutions_per_second":0.02238866403401865,"step_position":207},"timestamp":{"system_time_us":838436512}}
{"global_pose":{"position":{"x":0.526269105928749,"y":0.030000003192748897,"z":0.0},"rotation":{"w":1.0000000532124802,"x":0.0,"y":0.0,"z":0.0}},"ir_pose":{"position":{"x":0.6262691165712453,"y":0.030000003192748897,"z":0.0},"rotation":{"w":0.7071068376269066,"x":0.0,"y":0.0,"z":-0.7071068376269066}},"left_encoder_data_input":{"revolutions_per_second":101.41419602786351,"step_position":233},"line_following_statistics":{"average_speed":101.41419602786351,"time_spent_on_line":0.18000900000000003,"tracking_error":0.9285714285714286},"right_encoder_data_input":{"revolutions_per_second":101.41419602786351,"step_position":233},"timestamp":{"system_time_us":838446512}}
{"global_pose":{"position":{"x":0.5898812066291261,"y":0.030000003192748925,"z":0.0},"rotation":{"w":1.0000000532124802,"x":0.0,"y":0.0,"z":0.0}},"ir_pose":{"position":{"x":0.6898812172716224,"y":0.030000003192748925,"z":0.0},"rotation":{"w":0.7071068376269066,"x":0.0,"y":0.0,"z":-0.7071068376269066}},"left_encoder_data_input":{"revolutions_per_second":0.02238866403401865,"step_position":233},"line_following_statistics":{"average_speed":0.02238866403401865,"time_spent_on_line":0.19001100000000004,"tracking_error":0.9285714285714286},"right_encoder_data_input":{"revolutions_per_second":0.02238866403401865,"step_position":233},"timestamp":{"system_time_us":838456514}}
{"global_pose":{"position":{"x":0.5898953047909846,"y":0.03000000319274887,"z":0.0},"rotation":{"w":1.0000000532124802,"x":0.0,"y":0.0,"z":0.0}},"ir_pose":{"position":{"x":0.6898953154334809,"y":0.03000000319274887,"z":0.0},"rotation":{"w":0.7071068376269066,"x":0.0,"y":0.0,"z":-0.7071068376269066}},"left_encoder_data_input":{"revolutions_per_second":101.41419602786351,"step_position":258},"line_following_statistics":{"average_speed":101.41419602786351,"time_spent_on_line":0.20001100000000005,"tracking_error":0.9285714285714286},"right_encoder_data_input":{"revolutions_per_second":101.41419602786351,"step_position":258},"timestamp":{"system_time_us":838466514}}
{"global_pose":{"position":{"x":0.6542593065113604,"y":0.030000003192748925,"z":0.0},"rotation":{"w":1.0000000532124802,"x":0.0,"y":0.0,"z":0.0}},"ir_pose":{"position":{"x":0.7542593171538567,"y":0.030000003192748925,"z":0.0},"rotation":{"w":0.7071068376269066,"x":0.0,"y":0.0,"z":-0.7071068376269066}},"left_encoder_data_input":{"revolutions_per_second":0.02238866403401865,"step_position":258},"line_following_statistics":{"average_speed":0.02238866403401865,"time_spent_on_line":0.21001200000000006,"tracking_error":0.9285714285714286},"right_encoder_data_input":{"revolutions_per_second":0.02238866403401865,"step_position":258},"timestamp":{"system_time_us":838476515}}
{"global_pose":{"position":{"x":0.6542732260196013,"y":0.03000000319274887,"z":0.0},"rotation":{"w":1.0000000532124802,"x":0.0,"y":0.0,"z":0.0}},"ir_pose":{"position":{"x":0.7542732366620976,"y":0.03000000319274887,"z":0.0},"rotation":{"w":0.7071068376269066,"x":0.0,"y":0.0,"z":-0.7071068376269066}},"left_encoder_data_input":{"revolutions_per_second":101.41419602786351,"step_position":283},"line_following_statistics":{"average_speed":101.41419602786351,"time_spent_on_line":0.22001500000000007,"tracking_error":0.9285714285714286},"right_encoder_data_input":{"revolutions_per_second":101.41419602786351,"step_position":283},"timestamp":{"system_time_us":838486518}}
{"global_pose":{"position":{"x":0.7178024901669278,"y":0.03000000319274887,"z":0.0},"rotation":{"w":1.0000000532124802,"x":0.0,"y":0.0,"z":0.0}},"ir_pose":{"position":{"x":0.8178025008094241,"y":0.03000000319274887,"z":0.0},"rotation":{"w":0.7071068376269066,"x":0.0,"y":0.0,"z":-0.7071068376269066}},"left_encoder_data_input":{"revolutions_per_second":0.02238866403401865,"step_position":283},"line_following_statistics":{"average_speed":0.02238866403401865,"time_spent_on_line":0.23001500000000008,"tracking_error":0.9285714285714286},"right_encoder_data_input":{"revolutions_per_second":0.02238866403401865,"step_position":283},"timestamp":{"system_time_us":838496518}}
{"global_pose":{"position":{"x":0.7178165939556719,"y":0.03000000319274887,"z":0.0},"rotation":{"w":1.0000000532124802,"x":0.0,"y":0.0,"z":0.0}},"ir_pose":{"position":{"x":0.8178166045981682,"y":0.03000000319274887,"z":0.0},"rotation":{"w":0.7071068376269066,"x":0.0,"y":0.0,"z":-0.7071068376269066}},"left_encoder_data_input":{"revolutions_per_second":101.41419602786351,"step_position":309},"line_following_statistics":{"average_speed":101.41419602786351,"time_spent_on_line":0.2400150000000001,"tracking_error":0.9285714285714286},"right_encoder_data_input":{"revolutions_per_second":101.41419602786351,"step_position":309},"timestamp":{"system_time_us":838506518}}
{"global_pose":{"position":{"x":0.7815242752941844,"y":0.03000000319274887,"z":0.0},"rotation":{"w":1.0000000532124802,"x":0.0,"y":0.0,"z":0.0}},"ir_pose":{"position":{"x":0.8815242859366808,"y":0.03000000319274887,"z":0.0},"rotation":{"w":0.7071068376269066,"x":0.0,"y":0.0,"z":-0.7071068376269066}},"left_encoder_data_input":{"revolutions_per_second":0.02238866403401865,"step_position":309},"line_following_statistics":{"average_speed":0.02238866403401865,"time_spent_on_line":0.2500200000000001,"tracking_error":0.9285714285714286},"right_encoder_data_input":{"revolutions_per_second":0.02238866403401865,"step_position":309},"timestamp":{"system_time_us":838516523}}
{"global_pose":{"position":{"x":0.7815389881932944,"y":0.030000003192748925,"z":0.0},"rotation":{"w":1.0000000532124802,"x":0.0,"y":0.0,"z":0.0}},"ir_pose":{"position":{"x":0.8815389988357907,"y":0.030000003192748925,"z":0.0},"rotation":{"w":0.7071068376269066,"x":0.0,"y":0.0,"z":-0.7071068376269066}},"left_encoder_data_input":{"revolutions_per_second":101.41419602786351,"step_position":334},"line_following_statistics":{"average_speed":101.41419602786351,"time_spent_on_line":0.2600180000000001,"tracking_error":0.9285714285714286},"right_encoder_data_input":{"revolutions_per_second":101.41419602786351,"step_position":334},"timestamp":{"system_time_us":838526521}}
{"global_pose":{"position":{"x":0.8471646543370572,"y":0.03000000319274887,"z":0.0},"rotation":{"w":1.0000000532124802,"x":0.0,"y":0.0,"z":0.0}},"ir_pose":{"position":{"x":0.9471646649795535,"y":0.03000000319274887,"z":0.0},"rotation":{"w":0.7071068376269066,"x":0.0,"y":0.0,"z":-0.7071068376269066}},"left_encoder_data_input":{"revolutions_per_second":0.02238866403401865,"step_position":334},"line_following_statistics":{"average_speed":0.02238866403401865,"time_spent_on_line":0.27002100000000007,"tracking_error":0.9285714285714286},"right_encoder_data_input":{"revolutions_per_second":0.02238866403401865,"step_position":334},"timestamp":{"system_time_us":838536524}}
{"global_pose":{"position":{"x":0.8471776763570456,"y":0.030000003192748925,"z":0.0},"rotation":{"w":1.0000000532124802,"x":0.0,"y":0.0,"z":0.0}},"ir_pose":{"position":{"x":0.9471776869995419,"y":0.030000003192748925,"z":0.0},"rotation":{"w":0.7071068376269066,"x":0.0,"y":0.0,"z":-0.7071068376269066}},"left_encoder_data_input":{"revolutions_per_second":101.41419602786351,"step_position":360},"line_following_statistics":{"average_speed":101.41419602786351,"time_spent_on_line":0.28001800000000004,"tracking_error":0.9285714285714286},"right_encoder_data_input":{"revolutions_per_second":101.41419602786351,"step_position":360},"timestamp":{"system_time_us":838546521}}
{"global_pose":{"position":{"x":0.9109809383336935,"y":0.03000000319274887,"z":0.0},"rotation":{"w":1.0000000532124802,"x":0.0,"y":0.0,"z":0.0}},"ir_pose":{"position":{"x":1.0109809489761898,"y":0.03000000319274887,"z":0.0},"rotation":{"w":0.7071068376269066,"x":0.0,"y":0.0,"z":-0.7071068376269066}},"left_encoder_data_input":{"revolutions_per_second":0.02238866403401865,"step_position":360},"line_following_statistics":{"average_speed":0.02238866403401865,"time_spent_on_line":0.290019,"tracking_error":0.9285714285714286},"right_encoder_data_input":{"revolutions_per_second":0.02238866403401865,"step_position":360},"timestamp":{"system_time_us":838556522}}
{"global_pose":{"position":{"x":0.910995120898836,"y":0.030000003192748925,"z":0.0},"rotation":{"w":1.0000000532124802,"x":0.0,"y":0.0,"z":0.0}},"ir_pose":{"position":{"x":1.0109951315413324,"y":0.030000003192748925,"z":0.0},"rotation":{"w":0.7071068376269066,"x":0.0,"y":0.0,"z":-0.7071068376269066}},"left_encoder_data_input":{"revolutions_per_second":101.41419602786351,"step_position":388},"line_following_statistics":{"average_speed":101.41419602786351,"time_spent_on_line":0.300024,"tracking_error":0.9285714285714286},"right_encoder_data_input":{"revolutions_per_second":101.41419602786351,"step_position":388},"timestamp":{"system_time_us":838566527}}
{"global_pose":{"position":{"x":0.9822536726500449,"y":0.03000000319274887,"z":0.0},"rotation":{"w":1.0000000532124802,"x":0.0,"y":0.0,"z":0.0}},"ir_pose":{"position":{"x":1.0822536832925413,"y":0.03000000319274887,"z":0.0},"rotation":{"w":0.7071068376269066,"x":0.0,"y":0.0,"z":-0.7071068376269066}},"left_encoder_data_input":{"revolutions_per_second":0.02238866403401865,"step_position":388},"line_following_statistics":{"average_speed":0.02238866403401865,"time_spent_on_line":0.31115000000000004,"tracking_error":0.9285714285714286},"right_encoder_data_input":{"revolutions_per_second":0.02238866403401865,"step_position":388},"timestamp":{"system_time_us":838577653}}
{"global_pose":{"position":{"x":0.9822675358894298,"y":0.03000000319274887,"z":0.0},"rotation":{"w":1.0000000532124802,"x":0.0,"y":0.0,"z":0.0}},"ir_pose":{"position":{"x":1.0822675465319262,"y":0.03000000319274887,"z":0.0},"rotation":{"w":0.7071068376269066,"x":0.0,"y":0.0,"z":-0.7071068376269066}},"left_encoder_data_input":{"revolutions_per_second":101.41419602786351,"step_position":413},"line_following_statistics":{"average_speed":101.41419602786351,"time_spent_on_line":0.32114000000000004,"tracking_error":0.8571428571428571},"right_encoder_data_input":{"revolutions_per_second":101.41419602786351,"step_position":413},"timestamp":{"system_time_us":838587643}}
{"global_pose":{"position":{"x":1.0458477763770953,"y":0.03000000319274887,"z":0.0},"rotation":{"w":1.0000000532124802,"x":0.0,"y":0.0,"z":0.0}},"ir_pose":{"position":{"x":1.1458477870195916,"y":0.03000000319274887,"z":0.0},"rotation":{"w":0.7071068376269066,"x":0.0,"y":0.0,"z":-0.7071068376269066}},"left_encoder_data_input":{"revolutions_per_second":0.02238866403401865,"step_position":413},"line_following_statistics":{"average_speed":0.02238866403401865,"time_spent_on_line":0.331135,"tracking_error":0.8571428571428571},"right_encoder_data_input":{"revolutions_per_second":0.02238866403401865,"step_position":413},"timestamp":{"system_time_us":838597638}}
{"global_pose":{"position":{"x":1.0458618070163266,"y":0.03000000319274898,"z":0.0},"rotation":{"w":1.0000000532124802,"x":0.0,"y":0.0,"z":0.0}},"ir_pose":{"position":{"x":1.145861817658823,"y":0.03000000319274898,"z":0.0},"rotation":{"w":0.7071068376269066,"x":0.0,"y":0.0,"z":-0.7071068376269066}},"left_encoder_data_input":{"revolutions_per_second":101.41419602786351,"step_position":438},"line_following_statistics":{"average_speed":101.41419602786351,"time_spent_on_line":0.34114,"tracking_error":0.7857142857142857},"right_encoder_data_input":{"revolutions_per_second":101.41419602786351,"step_position":439},"timestamp":{"system_time_us":838607643}}
{"global_pose":{"position":{"x":1.1099772990775503,"y":0.03000000319274898,"z":0.0},"rotation":{"w":1.0000000532124802,"x":0.0,"y":0.0,"z":0.0}},"ir_pose":{"position":{"x":1.2099773097200466,"y":0.03000000319274898,"z":0.0},"rotation":{"w":0.7071068376269066,"x":0.0,"y":0.0,"z":-0.7071068376269066}},"left_encoder_data_input":{"revolutions_per_second":197.16516342492645,"step_position":488},"line_following_statistics":{"average_speed":101.41419602786351,"time_spent_on_line":0.34114,"tracking_error":0.7857142857142857},"right_encoder_data_input":{"revolutions_per_second":147.42391354633253,"step_position":475},"timestamp":{"system_time_us":838617646}}
{"global_pose":{"position":{"x":1.2174738111259842,"y":0.021617606090504005,"z":0.0},"rotation":{"w":0.9992431383032125,"x":0.0,"y":0.0,"z":-0.03890060383734384}},"ir_pose":{"position":{"x":1.3171711703726985,"y":0.013843373798440514,"z":0.0},"rotation":{"w":0.6790647364500502,"x":0.0,"y":0.0,"z":-0.734078499445034}},"left_encoder_data_input":{"revolutions_per_second":197.16516342492645,"step_position":537},"line_following_statistics":{"average_speed":172.2945384856295,"time_spent_on_line":0.34114,"tracking_error":0.7142857142857143},"right_encoder_data_input":{"revolutions_per_second":147.42391354633253,"step_position":512},"timestamp":{"system_time_us":838627647}}
{"global_pose":{"position":{"x":1.3243419152488118,"y":0.004820617426266716,"z":0.0},"rotation":{"w":0.9969635085859208,"x":0.0,"y":0.0,"z":-0.07787084803065841}},"ir_pose":{"position":{"x":1.4231291520967053,"y":-0.010706261347574533,"z":0.0},"rotation":{"w":0.6498966701087178,"x":0.0,"y":0.0,"z":-0.7600226824372082}},"left_encoder_data_input":{"revolutions_per_second":197.16516342492645,"step_position":586},"line_following_statistics":{"average_speed":172.2945384856295,"time_spent_on_line":0.351138,"tracking_error":0.07142857142857142},"right_encoder_data_input":{"revolutions_per_second":147.42391354633253,"step_position":549},"timestamp":{"system_time_us":838637645}}
{"global_pose":{"position":{"x":1.4299876302986037,"y":-0.020394257832119456,"z":0.0},"rotation":{"w":0.9931463776647029,"x":0.0,"y":0.0,"z":-0.11687762384837552}},"ir_pose":{"position":{"x":1.5272555651498114,"y":-0.04360957558313383,"z":0.0},"rotation":{"w":0.6196155944510511,"x":0.0,"y":0.0,"z":-0.7849055196331081}},"left_encoder_data_input":{"revolutions_per_second":0.02238866403401865,"step_position":586},"line_following_statistics":{"average_speed":0.02238866403401865,"time_spent_on_line":0.351138,"tracking_error":0.0},"right_encoder_data_input":{"revolutions_per_second":0.02238866403401865,"step_position":549},"timestamp":{"system_time_us":838647646}}
{"global_pose":{"position":{"x":1.4300012858199103,"y":-0.02039751704870163,"z":0.0},"rotation":{"w":0.9931463776647029,"x":0.0,"y":0.0,"z":-0.11687762384837552}},"ir_pose":{"position":{"x":1.527269220671118,"y":-0.043612834799716005,"z":0.0},"rotation":{"w":0.6196155944510511,"x":0.0,"y":0.0,"z":-0.7849055196331081}},"left_encoder_data_input":{"revolutions_per_second":0.02238866403401865,"step_position":586},"line_following_statistics":{"average_speed":0.02238866403401865,"time_spent_on_line":0.351138,"tracking_error":0.0},"right_encoder_data_input":{"revolutions_per_second":0.02238866403401865,"step_position":549},"timestamp":{"system_time_us":838657647}}
{"global_pose":{"position":{"x":1.4300149947044765,"y":-0.020400789001701503,"z":0.0},"rotation":{"w":0.9931463776647029,"x":0.0,"y":0.0,"z":-0.11687762384837552}},"ir_pose":{"position":{"x":1.5272829295556842,"y":-0.04361610675271588,"z":0.0},"rotation":{"w":0.6196155944510511,"x":0.0,"y":0.0,"z":-0.7849055196331081}},"left_encoder_data_input":{"revolutions_per_second":0.02238866403401865,"step_position":586},"line_following_statistics":{"average_speed":0.02238866403401865,"time_spent_on_line":0.351138,"tracking_error":0.0},"right_encoder_data_input":{"revolutions_per_second":0.02238866403401865,"step_position":549},"timestamp":{"system_time_us":838667647}}
{"global_pose":{"position":{"x":1.4300286255965862,"y":-0.0204040423399372,"z":0.0},"rotation":{"w":0.9931463776647029,"x":0.0,"y":0.0,"z":-0.11687762384837552}},"ir_pose":{"position":{"x":1.527296560447794,"y":-0.043619360090951576,"z":0.0},"rotation":{"w":0.6196155944510511,"x":0.0,"y":0.0,"z":-0.7849055196331081}},"left_encoder_data_input":{"revolutions_per_second":0.02238866403401865,"step_position":586},"line_following_statistics":{"average_speed":0.02238866403401865,"time_spent_on_line":0.351138,"tracking_error":0.0},"right_encoder_data_input":{"revolutions_per_second":0.02238866403401865,"step_position":549},"timestamp":{"system_time_us":838677650}}
{"global_pose":{"position":{"x":1.4300423768981023,"y":-0.020407324416755968,"z":0.0},"rotation":{"w":0.9931463776647029,"x":0.0,"y":0.0,"z":-0.11687762384837552}},"ir_pose":{"position":{"x":1.52731031174931,"y":-0.04362264216777034,"z":0.0},"rotation":{"w":0.6196155944510511,"x":0.0,"y":0.0,"z":-0.7849055196331081}},"left_encoder_data_input":{"revolutions_per_second":0.02238866403401865,"step_position":586},"line_following_statistics":{"average_speed":0.02238866403401865,"time_spent_on_line":0.351138,"tracking_error":0.0},"right_encoder_data_input":{"revolutions_per_second":0.02238866403401865,"step_position":549},"timestamp":{"system_time_us":838687649}}
{"global_pose":{"position":{"x":1.430056119989886,"y":-0.020410604534125798,"z":0.0},"rotation":{"w":0.9931463776647029,"x":0.0,"y":0.0,"z":-0.11687762384837552}},"ir_pose":{"position":{"x":1.5273240548410938,"y":-0.04362592228514017,"z":0.0},"rotation":{"w":0.6196155944510511,"x":0.0,"y":0.0,"z":-0.7849055196331081}},"left_encoder_data_input":{"revolutions_per_second":0.02238866403401865,"step_position":586},"line_following_statistics":{"average_speed":0.02238866403401865,"time_spent_on_line":0.351138,"tracking_error":0.0},"right_encoder_data_input":{"revolutions_per_second":0.02238866403401865,"step_position":549},"timestamp":{"system_time_us":838697655}}
{"global_pose":{"position":{"x":1.430069754986862,"y":-0.02041385885208591,"z":0.0},"rotation":{"w":0.9931463776647029,"x":0.0,"y":0.0,"z":-0.11687762384837552}},"ir_pose":{"position":{"x":1.5273376898380697,"y":-0.043629176603100284,"z":0.0},"rotation":{"w":0.6196155944510511,"x":0.0,"y":0.0,"z":-0.7849055196331081}},"left_encoder_data_input":{"revolutions_per_second":0.02238866403401865,"step_position":586},"line_following_statistics":{"average_speed":0.02238866403401865,"time_spent_on_line":0.351138,"tracking_error":0.0},"right_encoder_data_input":{"revolutions_per_second":0.02238866403401865,"step_position":549},"timestamp":{"system_time_us":838707651}}
{"global_pose":{"position":{"x":1.4300834200861896,"y":-0.02041712035469201,"z":0.0},"rotation":{"w":0.9931463776647029,"x":0.0,"y":0.0,"z":-0.11687762384837552}},"ir_pose":{"position":{"x":1.5273513549373974,"y":-0.043632438105706384,"z":0.0},"rotation":{"w":0.6196155944510511,"x":0.0,"y":0.0,"z":-0.7849055196331081}},"left_encoder_data_input":{"revolutions_per_second":0.02238866403401865,"step_position":586},"line_following_statistics":{"average_speed":0.02238866403401865,"time_spent_on_line":0.351138,"tracking_error":0.0},"right_encoder_data_input":{"revolutions_per_second":0.02238866403401865,"step_position":549},"timestamp":{"system_time_us":838717650}}
{"global_pose":{"position":{"x":1.4300971029732703,"y":-0.020420386102770305,"z":0.0},"rotation":{"w":0.9931463776647029,"x":0.0,"y":0.0,"z":-0.11687762384837552}},"ir_pose":{"position":{"x":1.527365037824478,"y":-0.04363570385378468,"z":0.0},"rotation":{"w":0.6196155944510511,"x":0.0,"y":0.0,"z":-0.7849055196331081}},"left_encoder_data_input":{"revolutions_per_second":0.02238866403401865,"step_position":586},"line_following_statistics":{"average_speed":0.02238866403401865,"time_spent_on_line":0.351138,"tracking_error":0.0},"right_encoder_data_input":{"revolutions_per_second":0.02238866403401865,"step_position":549},"timestamp":{"system_time_us":838727657}}
{"global_pose":{"position":{"x":1.4301107940700835,"y":-0.020423653810297537,"z":0.0},"rotation":{"w":0.9931463776647029,"x":0.0,"y":0.0,"z":-0.11687762384837552}},"ir_pose":{"position":{"x":1.5273787289212912,"y":-0.04363897156131191,"z":0.0},"rotation":{"w":0.6196155944510511,"x":0.0,"y":0.0,"z":-0.7849055196331081}},"left_encoder_data_input":{"revolutions_per_second":0.02238866403401865,"step_position":586},"line_following_statistics":{"average_speed":0.02238866403401865,"time_spent_on_line":0.351138,"tracking_error":0.0},"right_encoder_data_input":{"revolutions_per_second":0.02238866403401865,"step_position":549},"timestamp":{"system_time_us":838737658}}
{"global_pose":{"position":{"x":1.4301245412667334,"y":-0.02042693490739189,"z":0.0},"rotation":{"w":0.9931463776647029,"x":0.0,"y":0.0,"z":-0.11687762384837552}},"ir_pose":{"position":{"x":1.5273924761179412,"y":-0.043642252658406266,"z":0.0},"rotation":{"w":0.6196155944510511,"x":0.0,"y":0.0,"z":-0.7849055196331081}},"left_encoder_data_input":{"revolutions_per_second":0.02238866403401865,"step_position":586},"line_following_statistics":{"average_speed":0.02238866403401865,"time_spent_on_line":0.351138,"tracking_error":0.0},"right_encoder_data_input":{"revolutions_per_second":0.02238866403401865,"step_position":549},"timestamp":{"system_time_us":838747654}}
{"global_pose":{"position":{"x":1.4301381283736045,"y":-0.020430177795233706,"z":0.0},"rotation":{"w":0.9931463776647029,"x":0.0,"y":0.0,"z":-0.11687762384837552}},"ir_pose":{"position":{"x":1.5274060632248123,"y":-0.04364549554624808,"z":0.0},"rotation":{"w":0.6196155944510511,"x":0.0,"y":0.0,"z":-0.7849055196331081}},"left_encoder_data_input":{"revolutions_per_second":0.02238866403401865,"step_position":586},"line_following_statistics":{"average_speed":0.02238866403401865,"time_spent_on_line":0.351138,"tracking_error":0.0},"right_encoder_data_input":{"revolutions_per_second":0.02238866403401865,"step_position":549},"timestamp":{"system_time_us":838757662}}
{"global_pose":{"position":{"x":1.4301518304167273,"y":-0.02043344811535952,"z":0.0},"rotation":{"w":0.9931463776647029,"x":0.0,"y":0.0,"z":-0.11687762384837552}},"ir_pose":{"position":{"x":1.527419765267935,"y":-0.043648765866373895,"z":0.0},"rotation":{"w":0.6196155944510511,"x":0.0,"y":0.0,"z":-0.7849055196331081}},"left_encoder_data_input":{"revolutions_per_second":0.02238866403401865,"step_position":586},"line_following_statistics":{"average_speed":0.02238866403401865,"time_spent_on_line":0.351138,"tracking_error":0.0},"right_encoder_data_input":{"revolutions_per_second":0.02238866403401865,"step_position":549},"timestamp":{"system_time_us":838767660}}
{"global_pose":{"position":{"x":1.430165461308837,"y":-0.02043670145359522,"z":0.0},"rotation":{"w":0.9931463776647029,"x":0.0,"y":0.0,"z":-0.11687762384837552}},"ir_pose":{"position":{"x":1.5274333961600448,"y":-0.04365201920460959,"z":0.0},"rotation":{"w":0.6196155944510511,"x":0.0,"y":0.0,"z":-0.7849055196331081}},"left_encoder_data_input":{"revolutions_per_second":0.02238866403401865,"step_position":586},"line_following_statistics":{"average_speed":0.02238866403401865,"time_spent_on_line":0.351138,"tracking_error":0.0},"right_encoder_data_input":{"revolutions_per_second":0.02238866403401865,"step_position":549},"timestamp":{"system_time_us":838777659}}
{"global_pose":{"position":{"x":1.4301791455642068,"y":-0.020439967528248393,"z":0.0},"rotation":{"w":0.9931463776647029,"x":0.0,"y":0.0,"z":-0.11687762384837552}},"ir_pose":{"position":{"x":1.5274470804154145,"y":-0.04365528527926277,"z":0.0},"rotation":{"w":0.6196155944510511,"x":0.0,"y":0.0,"z":-0.7849055196331081}},"left_encoder_data_input":{"revolutions_per_second":0.02238866403401865,"step_position":586},"line_following_statistics":{"average_speed":0.02238866403401865,"time_spent_on_line":0.351138,"tracking_error":0.0},"right_encoder_data_input":{"revolutions_per_second":0.02238866403401865,"step_position":549},"timestamp":{"system_time_us":838787659}}
{"global_pose":{"position":{"x":1.4301929064437437,"y":-0.020443251891090863,"z":0.0},"rotation":{"w":0.9931463776647029,"x":0.0,"y":0.0,"z":-0.11687762384837552}},"ir_pose":{"position":{"x":1.5274608412949515,"y":-0.04365856964210524,"z":0.0},"rotation":{"w":0.6196155944510511,"x":0.0,"y":0.0,"z":-0.7849055196331081}},"left_encoder_data_input":{"revolutions_per_second":0.02238866403401865,"step_position":586},"line_following_statistics":{"average_speed":0.02238866403401865,"time_spent_on_line":0.351138,"tracking_error":0.0},"right_encoder_data_input":{"revolutions_per_second":0.02238866403401865,"step_position":549},"timestamp":{"system_time_us":838797660}}
{"global_pose":{"position":{"x":1.4302066262746194,"y":-0.020446526456689096,"z":0.0},"rotation":{"w":0.9931463776647029,"x":0.0,"y":0.0,"z":-0.11687762384837552}},"ir_pose":{"position":{"x":1.5274745611258271,"y":-0.04366184420770347,"z":0.0},"rotation":{"w":0.6196155944510511,"x":0.0,"y":0.0,"z":-0.7849055196331081}},"left_encoder_data_input":{"revolutions_per_second":0.02238866403401865,"step_position":586},"line_following_statistics":{"average_speed":0.02238866403401865,"time_spent_on_line":0.351138,"tracking_error":0.0},"right_encoder_data_input":{"revolutions_per_second":0.02238866403401865,"step_position":549},"timestamp":{"system_time_us":838807662}}
{"global_pose":{"position":{"x":1.4302202968471016,"y":-0.020449789265594154,"z":0.0},"rotation":{"w":0.9931463776647029,"x":0.0,"y":0.0,"z":-0.11687762384837552}},"ir_pose":{"position":{"x":1.5274882316983094,"y":-0.04366510701660853,"z":0.0},"rotation":{"w":0.6196155944510511,"x":0.0,"y":0.0,"z":-0.7849055196331081}},"left_encoder_data_input":{"revolutions_per_second":0.02238866403401865,"step_position":586},"line_following_statistics":{"average_speed":0.02238866403401865,"time_spent_on_line":0.351138,"tracking_error":0.0},"right_encoder_data_input":{"revolutions_per_second":0.02238866403401865,"step_position":549},"timestamp":{"system_time_us":838817661}}
{"global_pose":{"position":{"x":1.4302339400538098,"y":-0.02045304554300309,"z":0.0},"rotation":{"w":0.9931463776647029,"x":0.0,"y":0.0,"z":-0.11687762384837552}},"ir_pose":{"position":{"x":1.5275018749050175,"y":-0.043668363294017465,"z":0.0},"rotation":{"w":0.6196155944510511,"x":0.0,"y":0.0,"z":-0.7849055196331081}},"left_encoder_data_input":{"revolutions_per_second":0.02238866403401865,"step_position":586},"line_following_statistics":{"average_speed":0.02238866403401865,"time_spent_on_line":0.351138,"tracking_error":0.0},"right_encoder_data_input":{"revolutions_per_second":0.02238866403401865,"step_position":549},"timestamp":{"system_time_us":838827661}}
{"global_pose":{"position":{"x":1.4302476051531374,"y":-0.020456307045608968,"z":0.0},"rotation":{"w":0.9931463776647029,"x":0.0,"y":0.0,"z":-0.11687762384837552}},"ir_pose":{"position":{"x":1.5275155400043452,"y":-0.04367162479662334,"z":0.0},"rotation":{"w":0.6196155944510511,"x":0.0,"y":0.0,"z":-0.7849055196331081}},"left_encoder_data_input":{"revolutions_per_second":0.02238866403401865,"step_position":586},"line_following_statistics":{"average_speed":0.02238866403401865,"time_spent_on_line":0.351138,"tracking_error":0.0},"right_encoder_data_input":{"revolutions_per_second":0.02238866403401865,"step_position":549},"timestamp":{"system_time_us":838837665}}
{"global_pose":{"position":{"x":1.4302613605595198,"y":-0.02045959010215237,"z":0.0},"rotation":{"w":0.9931463776647029,"x":0.0,"y":0.0,"z":-0.11687762384837552}},"ir_pose":{"position":{"x":1.5275292954107276,"y":-0.043674907853166745,"z":0.0},"rotation":{"w":0.6196155944510511,"x":0.0,"y":0.0,"z":-0.7849055196331081}},"left_encoder_data_input":{"revolutions_per_second":0.02238866403401865,"step_position":586},"line_following_statistics":{"average_speed":0.02238866403401865,"time_spent_on_line":0.351138,"tracking_error":0.0},"right_encoder_data_input":{"revolutions_per_second":0.02238866403401865,"step_position":549},"timestamp":{"system_time_us":838847668}}
{"global_pose":{"position":{"x":1.430275103651304,"y":-0.02046287021952231,"z":0.0},"rotation":{"w":0.9931463776647029,"x":0.0,"y":0.0,"z":-0.11687762384837552}},"ir_pose":{"position":{"x":1.5275430385025117,"y":-0.043678187970536686,"z":0.0},"rotation":{"w":0.6196155944510511,"x":0.0,"y":0.0,"z":-0.7849055196331081}},"left_encoder_data_input":{"revolutions_per_second":0.02238866403401865,"step_position":586},"line_following_statistics":{"average_speed":0.02238866403401865,"time_spent_on_line":0.351138,"tracking_error":0.0},"right_encoder_data_input":{"revolutions_per_second":0.02238866403401865,"step_position":549},"timestamp":{"system_time_us":838857667}}
{"global_pose":{"position":{"x":1.4302886524460914,"y":-0.020466103963269533,"z":0.0},"rotation":{"w":0.9931463776647029,"x":0.0,"y":0.0,"z":-0.11687762384837552}},"ir_pose":{"position":{"x":1.5275565872972992,"y":-0.04368142171428391,"z":0.0},"rotation":{"w":0.6196155944510511,"x":0.0,"y":0.0,"z":-0.7849055196331081}},"left_encoder_data_input":{"revolutions_per_second":0.02238866403401865,"step_position":586},"line_following_statistics":{"average_speed":0.02238866403401865,"time_spent_on_line":0.351138,"tracking_error":0.0},"right_encoder_data_input":{"revolutions_per_second":0.02238866403401865,"step_position":549},"timestamp":{"system_time_us":838867668}}
{"global_pose":{"position":{"x":1.430302349016059,"y":-0.020469372977095945,"z":0.0},"rotation":{"w":0.9931463776647029,"x":0.0,"y":0.0,"z":-0.11687762384837552}},"ir_pose":{"position":{"x":1.5275702838672667,"y":-0.04368469072811032,"z":0.0},"rotation":{"w":0.6196155944510511,"x":0.0,"y":0.0,"z":-0.7849055196331081}},"left_encoder_data_input":{"revolutions_per_second":0.02238866403401865,"step_position":586},"line_following_statistics":{"average_speed":0.02238866403401865,"time_spent_on_line":0.351138,"tracking_error":0.0},"right_encoder_data_input":{"revolutions_per_second":0.02238866403401865,"step_position":549},"timestamp":{"system_time_us":838877670}}
{"global_pose":{"position":{"x":1.430315959383838,"y":-0.02047262141670947,"z":0.0},"rotation":{"w":0.9931463776647029,"x":0.0,"y":0.0,"z":-0.11687762384837552}},"ir_pose":{"position":{"x":1.5275838942350457,"y":-0.043687939167723844,"z":0.0},"rotation":{"w":0.6196155944510511,"x":0.0,"y":0.0,"z":-0.7849055196331081}},"left_encoder_data_input":{"revolutions_per_second":0.02238866403401865,"step_position":586},"line_following_statistics":{"average_speed":0.02238866403401865,"time_spent_on_line":0.351138,"tracking_error":0.0},"right_encoder_data_input":{"revolutions_per_second":0.02238866403401865,"step_position":549},"timestamp":{"system_time_us":838887670}}
{"global_pose":{"position":{"x":1.430329665531827,"y":-0.020475892716559696,"z":0.0},"rotation":{"w":0.9931463776647029,"x":0.0,"y":0.0,"z":-0.11687762384837552}},"ir_pose":{"position":{"x":1.5275976003830347,"y":-0.04369121046757407,"z":0.0},"rotation":{"w":0.6196155944510511,"x":0.0,"y":0.0,"z":-0.7849055196331081}},"left_encoder_data_input":{"revolutions_per_second":0.02238866403401865,"step_position":586},"line_following_statistics":{"average_speed":0.02238866403401865,"time_spent_on_line":0.351138,"tracking_error":0.0},"right_encoder_data_input":{"revolutions_per_second":0.02238866403401865,"step_position":549},"timestamp":{"system_time_us":838897670}}
{"global_pose":{"position":{"x":1.4303434127284766,"y":-0.02047917381365405,"z":0.0},"rotation":{"w":0.9931463776647029,"x":0.0,"y":0.0,"z":-0.11687762384837552}},"ir_pose":{"position":{"x":1.5276113475796844,"y":-0.043694491564668425,"z":0.0},"rotation":{"w":0.6196155944510511,"x":0.0,"y":0.0,"z":-0.7849055196331081}},"left_encoder_data_input":{"revolutions_per_second":0.02238866403401865,"step_position":586},"line_following_statistics":{"average_speed":0.02238866403401865,"time_spent_on_line":0.351138,"tracking_error":0.0},"right_encoder_data_input":{"revolutions_per_second":0.02238866403401865,"step_position":549},"timestamp":{"system_time_us":838907671}}
{"global_pose":{"position":{"x":1.430357068249783,"y":-0.020482433030236336,"z":0.0},"rotation":{"w":0.9931463776647029,"x":0.0,"y":0.0,"z":-0.11687762384837552}},"ir_pose":{"position":{"x":1.5276250031009908,"y":-0.04369775078125071,"z":0.0},"rotation":{"w":0.6196155944510511,"x":0.0,"y":0.0,"z":-0.7849055196331081}},"left_encoder_data_input":{"revolutions_per_second":0.02238866403401865,"step_position":587},"line_following_statistics":{"average_speed":0.02238866403401865,"time_spent_on_line":0.351138,"tracking_error":0.0},"right_encoder_data_input":{"revolutions_per_second":0.02238866403401865,"step_position":549},"timestamp":{"system_time_us":838917675}}
{"global_pose":{"position":{"x":1.4303707785026383,"y":-0.020485705309810753,"z":0.0},"rotation":{"w":0.9931463776647029,"x":0.0,"y":0.0,"z":-0.11687762384837552}},"ir_pose":{"position":{"x":1.527638713353846,"y":-0.04370102306082513,"z":0.0},"rotation":{"w":0.6196155944510511,"x":0.0,"y":0.0,"z":-0.7849055196331081}},"left_encoder_data_input":{"revolutions_per_second":0.02238866403401865,"step_position":587},"line_following_statistics":{"average_speed":0.02238866403401865,"time_spent_on_line":0.351138,"tracking_error":0.0},"right_encoder_data_input":{"revolutions_per_second":0.02238866403401865,"step_position":549},"timestamp":{"system_time_us":838927674}}
{"global_pose":{"position":{"x":1.4303844723360286,"y":-0.02048897367048763,"z":0.0},"rotation":{"w":0.9931463776647029,"x":0.0,"y":0.0,"z":-0.11687762384837552}},"ir_pose":{"position":{"x":1.5276524071872364,"y":-0.043704291421502006,"z":0.0},"rotation":{"w":0.6196155944510511,"x":0.0,"y":0.0,"z":-0.7849055196331081}},"left_encoder_data_input":{"revolutions_per_second":0.02238866403401865,"step_position":587},"line_following_statistics":{"average_speed":0.02238866403401865,"time_spent_on_line":0.351138,"tracking_error":0.0},"right_encoder_data_input":{"revolutions_per_second":0.02238866403401865,"step_position":549},"timestamp":{"system_time_us":838937675}}
{"global_pose":{"position":{"x":1.4303981634328418,"y":-0.020492241378014864,"z":0.0},"rotation":{"w":0.9931463776647029,"x":0.0,"y":0.0,"z":-0.11687762384837552}},"ir_pose":{"position":{"x":1.5276660982840495,"y":-0.04370755912902924,"z":0.0},"rotation":{"w":0.6196155944510511,"x":0.0,"y":0.0,"z":-0.7849055196331081}},"left_encoder_data_input":{"revolutions_per_second":0.02238866403401865,"step_position":587},"line_following_statistics":{"average_speed":0.02238866403401865,"time_spent_on_line":0.351138,"tracking_error":0.0},"right_encoder_data_input":{"revolutions_per_second":0.02238866403401865,"step_position":549},"timestamp":{"system_time_us":838947677}}
{"global_pose":{"position":{"x":1.4304118285321692,"y":-0.020495502880620853,"z":0.0},"rotation":{"w":0.9931463776647029,"x":0.0,"y":0.0,"z":-0.11687762384837552}},"ir_pose":{"position":{"x":1.527679763383377,"y":-0.04371082063163523,"z":0.0},"rotation":{"w":0.6196155944510511,"x":0.0,"y":0.0,"z":-0.7849055196331081}},"left_encoder_data_input":{"revolutions_per_second":0.02238866403401865,"step_position":587},"line_following_statistics":{"average_speed":0.02238866403401865,"time_spent_on_line":0.351138,"tracking_error":0.0},"right_encoder_data_input":{"revolutions_per_second":0.02238866403401865,"step_position":549},"timestamp":{"system_time_us":838957676}}
{"global_pose":{"position":{"x":1.4304255114192501,"y":-0.02049876862869926,"z":0.0},"rotation":{"w":0.9931463776647029,"x":0.0,"y":0.0,"z":-0.11687762384837552}},"ir_pose":{"position":{"x":1.5276934462704579,"y":-0.043714086379713635,"z":0.0},"rotation":{"w":0.6196155944510511,"x":0.0,"y":0.0,"z":-0.7849055196331081}},"left_encoder_data_input":{"revolutions_per_second":0.02238866403401865,"step_position":587},"line_following_statistics":{"average_speed":0.02238866403401865,"time_spent_on_line":0.351138,"tracking_error":0.0},"right_encoder_data_input":{"revolutions_per_second":0.02238866403401865,"step_position":549},"timestamp":{"system_time_us":838967677}}
{"global_pose":{"position":{"x":1.4304391997794854,"y":-0.020502035683076958,"z":0.0},"rotation":{"w":0.9931463776647029,"x":0.0,"y":0.0,"z":-0.11687762384837552}},"ir_pose":{"position":{"x":1.5277071346306932,"y":-0.04371735343409133,"z":0.0},"rotation":{"w":0.6196155944510511,"x":0.0,"y":0.0,"z":-0.7849055196331081}},"left_encoder_data_input":{"revolutions_per_second":0.02238866403401865,"step_position":587},"line_following_statistics":{"average_speed":0.02238866403401865,"time_spent_on_line":0.351138,"tracking_error":0.0},"right_encoder_data_input":{"revolutions_per_second":0.02238866403401865,"step_position":549},"timestamp":{"system_time_us":838977676}}
{"global_pose":{"position":{"x":1.4304528347764616,"y":-0.02050529000103707,"z":0.0},"rotation":{"w":0.9931463776647029,"x":0.0,"y":0.0,"z":-0.11687762384837552}},"ir_pose":{"position":{"x":1.5277207696276693,"y":-0.043720607752051444,"z":0.0},"rotation":{"w":0.6196155944510511,"x":0.0,"y":0.0,"z":-0.7849055196331081}},"left_encoder_data_input":{"revolutions_per_second":0.02238866403401865,"step_position":587},"line_following_statistics":{"average_speed":0.02238866403401865,"time_spent_on_line":0.351138,"tracking_error":0.0},"right_encoder_data_input":{"revolutions_per_second":0.02238866403401865,"step_position":549},"timestamp":{"system_time_us":838987681}}
{"global_pose":{"position":{"x":1.4304665614487808,"y":-0.02050856619950925,"z":0.0},"rotation":{"w":0.9931463776647029,"x":0.0,"y":0.0,"z":-0.11687762384837552}},"ir_pose":{"position":{"x":1.5277344962999886,"y":-0.04372388395052362,"z":0.0},"rotation":{"w":0.6196155944510511,"x":0.0,"y":0.0,"z":-0.7849055196331081}},"left_encoder_data_input":{"revolutions_per_second":0.02238866403401865,"step_position":587},"line_following_statistics":{"average_speed":0.02238866403401865,"time_spent_on_line":0.351138,"tracking_error":0.0},"right_encoder_data_input":{"revolutions_per_second":0.02238866403401865,"step_position":549},"timestamp":{"system_time_us":838997682}}
{"global_pose":{"position":{"x":1.4304802634919036,"y":-0.02051183651963495,"z":0.0},"rotation":{"w":0.9931463776647029,"x":0.0,"y":0.0,"z":-0.11687762384837552}},"ir_pose":{"position":{"x":1.5277481983431114,"y":-0.04372715427064933,"z":0.0},"rotation":{"w":0.6196155944510511,"x":0.0,"y":0.0,"z":-0.7849055196331081}},"left_encoder_data_input":{"revolutions_per_second":0.02238866403401865,"step_position":587},"line_following_statistics":{"average_speed":0.02238866403401865,"time_spent_on_line":0.351138,"tracking_error":0.0},"right_encoder_data_input":{"revolutions_per_second":0.02238866403401865,"step_position":549},"timestamp":{"system_time_us":839007682}}
{"global_pose":{"position":{"x":1.4304939025937458,"y":-0.020515091817319475,"z":0.0},"rotation":{"w":0.9931463776647029,"x":0.0,"y":0.0,"z":-0.11687762384837552}},"ir_pose":{"position":{"x":1.5277618374449535,"y":-0.04373040956833385,"z":0.0},"rotation":{"w":0.6196155944510511,"x":0.0,"y":0.0,"z":-0.7849055196331081}},"left_encoder_data_input":{"revolutions_per_second":0.02238866403401865,"step_position":587},"line_following_statistics":{"average_speed":0.02238866403401865,"time_spent_on_line":0.351138,"tracking_error":0.0},"right_encoder_data_input":{"revolutions_per_second":0.02238866403401865,"step_position":549},"timestamp":{"system_time_us":839017682}}
{"global_pose":{"position":{"x":1.4305076320026424,"y":-0.02051836866894141,"z":0.0},"rotation":{"w":0.9931463776647029,"x":0.0,"y":0.0,"z":-0.11687762384837552}},"ir_pose":{"position":{"x":1.5277755668538502,"y":-0.043733686419955786,"z":0.0},"rotation":{"w":0.6196155944510511,"x":0.0,"y":0.0,"z":-0.7849055196331081}},"left_encoder_data_input":{"revolutions_per_second":0.02238866403401865,"step_position":587},"line_following_statistics":{"average_speed":0.02238866403401865,"time_spent_on_line":0.351138,"tracking_error":0.0},"right_encoder_data_input":{"revolutions_per_second":0.02238866403401865,"step_position":549},"timestamp":{"system_time_us":839027684}}
{"global_pose":{"position":{"x":1.4305212943653924,"y":-0.020521629518397644,"z":0.0},"rotation":{"w":0.9931463776647029,"x":0.0,"y":0.0,"z":-0.11687762384837552}},"ir_pose":{"position":{"x":1.5277892292166002,"y":-0.04373694726941202,"z":0.0},"rotation":{"w":0.6196155944510511,"x":0.0,"y":0.0,"z":-0.7849055196331081}},"left_encoder_data_input":{"revolutions_per_second":0.02238866403401865,"step_position":587},"line_following_statistics":{"average_speed":0.02238866403401865,"time_spent_on_line":0.351138,"tracking_error":0.0},"right_encoder_data_input":{"revolutions_per_second":0.02238866403401865,"step_position":549},"timestamp":{"system_time_us":839037685}}
{"global_pose":{"position":{"x":1.4305350032499586,"y":-0.020524901471397294,"z":0.0},"rotation":{"w":0.9931463776647029,"x":0.0,"y":0.0,"z":-0.11687762384837552}},"ir_pose":{"position":{"x":1.5278029381011664,"y":-0.04374021922241167,"z":0.0},"rotation":{"w":0.6196155944510511,"x":0.0,"y":0.0,"z":-0.7849055196331081}},"left_encoder_data_input":{"revolutions_per_second":0.02238866403401865,"step_position":587},"line_following_statistics":{"average_speed":0.02238866403401865,"time_spent_on_line":0.351138,"tracking_error":0.0},"right_encoder_data_input":{"revolutions_per_second":0.02238866403401865,"step_position":549},"timestamp":{"system_time_us":839047685}}
{"global_pose":{"position":{"x":1.4305486204591813,"y":-0.020528151543885098,"z":0.0},"rotation":{"w":0.9931463776647029,"x":0.0,"y":0.0,"z":-0.11687762384837552}},"ir_pose":{"position":{"x":1.527816555310389,"y":-0.04374346929489947,"z":0.0},"rotation":{"w":0.6196155944510511,"x":0.0,"y":0.0,"z":-0.7849055196331081}},"left_encoder_data_input":{"revolutions_per_second":0.02238866403401865,"step_position":587},"line_following_statistics":{"average_speed":0.02238866403401865,"time_spent_on_line":0.351138,"tracking_error":0.0},"right_encoder_data_input":{"revolutions_per_second":0.02238866403401865,"step_position":549},"timestamp":{"system_time_us":839057687}}
{"global_pose":{"position":{"x":1.4305624648043298,"y":-0.020531455827790923,"z":0.0},"rotation":{"w":0.9931463776647029,"x":0.0,"y":0.0,"z":-0.11687762384837552}},"ir_pose":{"position":{"x":1.5278303996555376,"y":-0.0437467735788053,"z":0.0},"rotation":{"w":0.6196155944510511,"x":0.0,"y":0.0,"z":-0.7849055196331081}},"left_encoder_data_input":{"revolutions_per_second":0.02238866403401865,"step_position":587},"line_following_statistics":{"average_speed":0.02238866403401865,"time_spent_on_line":0.351138,"tracking_error":0.0},"right_encoder_data_input":{"revolutions_per_second":0.02238866403401865,"step_position":549},"timestamp":{"system_time_us":839067687}}
{"global_pose":{"position":{"x":1.430577236849222,"y":-0.02053498152941624,"z":0.0},"rotation":{"w":0.9931463776647029,"x":0.0,"y":0.0,"z":-0.11687762384837552}},"ir_pose":{"position":{"x":1.5278451717004298,"y":-0.043750299280430616,"z":0.0},"rotation":{"w":0.6196155944510511,"x":0.0,"y":0.0,"z":-0.7849055196331081}},"left_encoder_data_input":{"revolutions_per_second":0.02238866403401865,"step_position":587},"line_following_statistics":{"average_speed":0.02238866403401865,"time_spent_on_line":0.351138,"tracking_error":0.0},"right_encoder_data_input":{"revolutions_per_second":0.02238866403401865,"step_position":549},"timestamp":{"system_time_us":839078576}}
{"global_pose":{"position":{"x":1.4305909977287592,"y":-0.0205382658922586,"z":0.0},"rotation":{"w":0.9931463776647029,"x":0.0,"y":0.0,"z":-0.11687762384837552}},"ir_pose":{"position":{"x":1.527858932579967,"y":-0.043753583643272975,"z":0.0},"rotation":{"w":0.6196155944510511,"x":0.0,"y":0.0,"z":-0.7849055196331081}},"left_encoder_data_input":{"revolutions_per_second":0.02238866403401865,"step_position":587},"line_following_statistics":{"average_speed":0.02238866403401865,"time_spent_on_line":0.351138,"tracking_error":0.0},"right_encoder_data_input":{"revolutions_per_second":0.02238866403401865,"step_position":549},"timestamp":{"system_time_us":839088575}}
{"global_pose":{"position":{"x":1.43060463819889,"y":-0.020541521516518002,"z":0.0},"rotation":{"w":0.9931463776647029,"x":0.0,"y":0.0,"z":-0.11687762384837552}},"ir_pose":{"position":{"x":1.5278725730500977,"y":-0.04375683926753238,"z":0.0},"rotation":{"w":0.6196155944510511,"x":0.0,"y":0.0,"z":-0.7849055196331081}},"left_encoder_data_input":{"revolutions_per_second":0.02238866403401865,"step_position":587},"line_following_statistics":{"average_speed":0.02238866403401865,"time_spent_on_line":0.351138,"tracking_error":0.0},"right_encoder_data_input":{"revolutions_per_second":0.02238866403401865,"step_position":549},"timestamp":{"system_time_us":839098573}}
{"global_pose":{"position":{"x":1.4306182937201966,"y":-0.020544780733100176,"z":0.0},"rotation":{"w":0.9931463776647029,"x":0.0,"y":0.0,"z":-0.11687762384837552}},"ir_pose":{"position":{"x":1.5278862285714043,"y":-0.04376009848411455,"z":0.0},"rotation":{"w":0.6196155944510511,"x":0.0,"y":0.0,"z":-0.7849055196331081}},"left_encoder_data_input":{"revolutions_per_second":0.02238866403401865,"step_position":587},"line_following_statistics":{"average_speed":0.02238866403401865,"time_spent_on_line":0.351138,"tracking_error":0.0},"right_encoder_data_input":{"revolutions_per_second":0.02238866403401865,"step_position":549},"timestamp":{"system_time_us":839108577}}
{"global_pose":{"position":{"x":1.430631986185298,"y":-0.020548048767202287,"z":0.0},"rotation":{"w":0.9931463776647029,"x":0.0,"y":0.0,"z":-0.11687762384837552}},"ir_pose":{"position":{"x":1.5278999210365058,"y":-0.04376336651821666,"z":0.0},"rotation":{"w":0.6196155944510511,"x":0.0,"y":0.0,"z":-0.7849055196331081}},"left_encoder_data_input":{"revolutions_per_second":0.02238866403401865,"step_position":587},"line_following_statistics":{"average_speed":0.02238866403401865,"time_spent_on_line":0.351138,"tracking_error":0.0},"right_encoder_data_input":{"revolutions_per_second":0.02238866403401865,"step_position":549},"timestamp":{"system_time_us":839118578}}
{"global_pose":{"position":{"x":1.4306456854918435,"y":-0.020551318434178456,"z":0.0},"rotation":{"w":0.9931463776647029,"x":0.0,"y":0.0,"z":-0.11687762384837552}},"ir_pose":{"position":{"x":1.5279136203430512,"y":-0.04376663618519283,"z":0.0},"rotation":{"w":0.6196155944510511,"x":0.0,"y":0.0,"z":-0.7849055196331081}},"left_encoder_data_input":{"revolutions_per_second":0.02238866403401865,"step_position":587},"line_following_statistics":{"average_speed":0.02238866403401865,"time_spent_on_line":0.351138,"tracking_error":0.0},"right_encoder_data_input":{"revolutions_per_second":0.02238866403401865,"step_position":549},"timestamp":{"system_time_us":839128579}}
{"global_pose":{"position":{"x":1.430659368378924,"y":-0.020554584182256752,"z":0.0},"rotation":{"w":0.9931463776647029,"x":0.0,"y":0.0,"z":-0.11687762384837552}},"ir_pose":{"position":{"x":1.5279273032301317,"y":-0.04376990193327113,"z":0.0},"rotation":{"w":0.6196155944510511,"x":0.0,"y":0.0,"z":-0.7849055196331081}},"left_encoder_data_input":{"revolutions_per_second":0.02238866403401865,"step_position":587},"line_following_statistics":{"average_speed":0.02238866403401865,"time_spent_on_line":0.351138,"tracking_error":0.0},"right_encoder_data_input":{"revolutions_per_second":0.02238866403401865,"step_position":549},"timestamp":{"system_time_us":839138580}}
{"global_pose":{"position":{"x":1.4306730608440255,"y":-0.020557852216358863,"z":0.0},"rotation":{"w":0.9931463776647029,"x":0.0,"y":0.0,"z":-0.11687762384837552}},"ir_pose":{"position":{"x":1.5279409956952332,"y":-0.04377316996737324,"z":0.0},"rotation":{"w":0.6196155944510511,"x":0.0,"y":0.0,"z":-0.7849055196331081}},"left_encoder_data_input":{"revolutions_per_second":0.02238866403401865,"step_position":587},"line_following_statistics":{"average_speed":0.02238866403401865,"time_spent_on_line":0.351138,"tracking_error":0.0},"right_encoder_data_input":{"revolutions_per_second":0.02238866403401865,"step_position":549},"timestamp":{"system_time_us":839148581}}
{"global_pose":{"position":{"x":1.430686843616182,"y":-0.020561141804398164,"z":0.0},"rotation":{"w":0.9931463776647029,"x":0.0,"y":0.0,"z":-0.11687762384837552}},"ir_pose":{"position":{"x":1.5279547784673897,"y":-0.04377645955541254,"z":0.0},"rotation":{"w":0.6196155944510511,"x":0.0,"y":0.0,"z":-0.7849055196331081}},"left_encoder_data_input":{"revolutions_per_second":0.02238866403401865,"step_position":587},"line_following_statistics":{"average_speed":0.02238866403401865,"time_spent_on_line":0.351138,"tracking_error":0.0},"right_encoder_data_input":{"revolutions_per_second":0.02238866403401865,"step_position":549},"timestamp":{"system_time_us":839158582}}
{"global_pose":{"position":{"x":1.430700397884124,"y":-0.020564376854444788,"z":0.0},"rotation":{"w":0.9931463776647029,"x":0.0,"y":0.0,"z":-0.11687762384837552}},"ir_pose":{"position":{"x":1.5279683327353317,"y":-0.04377969460545916,"z":0.0},"rotation":{"w":0.6196155944510511,"x":0.0,"y":0.0,"z":-0.7849055196331081}},"left_encoder_data_input":{"revolutions_per_second":0.02238866403401865,"step_position":587},"line_following_statistics":{"average_speed":0.02238866403401865,"time_spent_on_line":0.351138,"tracking_error":0.0},"right_encoder_data_input":{"revolutions_per_second":0.02238866403401865,"step_position":549},"timestamp":{"system_time_us":839168582}}
{"global_pose":{"position":{"x":1.430714121819866,"y":-0.020567652399767322,"z":0.0},"rotation":{"w":0.9931463776647029,"x":0.0,"y":0.0,"z":-0.11687762384837552}},"ir_pose":{"position":{"x":1.5279820566710738,"y":-0.0437829701507817,"z":0.0},"rotation":{"w":0.6196155944510511,"x":0.0,"y":0.0,"z":-0.7849055196331081}},"left_encoder_data_input":{"revolutions_per_second":0.02238866403401865,"step_position":587},"line_following_statistics":{"average_speed":0.02238866403401865,"time_spent_on_line":0.351138,"tracking_error":0.0},"right_encoder_data_input":{"revolutions_per_second":0.02238866403401865,"step_position":549},"timestamp":{"system_time_us":839178585}}
{"global_pose":{"position":{"x":1.430727796497215,"y":-0.020570916188397015,"z":0.0},"rotation":{"w":0.9931463776647029,"x":0.0,"y":0.0,"z":-0.11687762384837552}},"ir_pose":{"position":{"x":1.5279957313484227,"y":-0.04378623393941139,"z":0.0},"rotation":{"w":0.6196155944510511,"x":0.0,"y":0.0,"z":-0.7849055196331081}},"left_encoder_data_input":{"revolutions_per_second":0.02238866403401865,"step_position":587},"line_following_statistics":{"average_speed":0.02238866403401865,"time_spent_on_line":0.351138,"tracking_error":0.0},"right_encoder_data_input":{"revolutions_per_second":0.02238866403401865,"step_position":549},"timestamp":{"system_time_us":839188586}}
{"global_pose":{"position":{"x":1.4307414958037596,"y":-0.020574185855373073,"z":0.0},"rotation":{"w":0.9931463776647029,"x":0.0,"y":0.0,"z":-0.11687762384837552}},"ir_pose":{"position":{"x":1.5280094306549674,"y":-0.04378950360638745,"z":0.0},"rotation":{"w":0.6196155944510511,"x":0.0,"y":0.0,"z":-0.7849055196331081}},"left_encoder_data_input":{"revolutions_per_second":0.02238866403401865,"step_position":587},"line_following_statistics":{"average_speed":0.02238866403401865,"time_spent_on_line":0.351138,"tracking_error":0.0},"right_encoder_data_input":{"revolutions_per_second":0.02238866403401865,"step_position":549},"timestamp":{"system_time_us":839198583}}
{"global_pose":{"position":{"x":1.4307551308007358,"y":-0.020577440173333184,"z":0.0},"rotation":{"w":0.9931463776647029,"x":0.0,"y":0.0,"z":-0.11687762384837552}},"ir_pose":{"position":{"x":1.5280230656519436,"y":-0.04379275792434756,"z":0.0},"rotation":{"w":0.6196155944510511,"x":0.0,"y":0.0,"z":-0.7849055196331081}},"left_encoder_data_input":{"revolutions_per_second":0.02238866403401865,"step_position":587},"line_following_statistics":{"average_speed":0.02238866403401865,"time_spent_on_line":0.351138,"tracking_error":0.0},"right_encoder_data_input":{"revolutions_per_second":0.02238866403401865,"step_position":549},"timestamp":{"system_time_us":839208585}}
{"global_pose":{"position":{"x":1.4307688697876535,"y":-0.020580719310978712,"z":0.0},"rotation":{"w":0.9931463776647029,"x":0.0,"y":0.0,"z":-0.11687762384837552}},"ir_pose":{"position":{"x":1.5280368046388613,"y":-0.04379603706199309,"z":0.0},"rotation":{"w":0.6196155944510511,"x":0.0,"y":0.0,"z":-0.7849055196331081}},"left_encoder_data_input":{"revolutions_per_second":0.02238866403401865,"step_position":587},"line_following_statistics":{"average_speed":0.02238866403401865,"time_spent_on_line":0.351138,"tracking_error":0.0},"right_encoder_data_input":{"revolutions_per_second":0.02238866403401865,"step_position":549},"timestamp":{"system_time_us":839218586}}
{"global_pose":{"position":{"x":1.4307824582628133,"y":-0.020583962525395183,"z":0.0},"rotation":{"w":0.9931463776647029,"x":0.0,"y":0.0,"z":-0.11687762384837552}},"ir_pose":{"position":{"x":1.528050393114021,"y":-0.04379928027640956,"z":0.0},"rotation":{"w":0.6196155944510511,"x":0.0,"y":0.0,"z":-0.7849055196331081}},"left_encoder_data_input":{"revolutions_per_second":0.02238866403401865,"step_position":587},"line_following_statistics":{"average_speed":0.02238866403401865,"time_spent_on_line":0.351138,"tracking_error":0.0},"right_encoder_data_input":{"revolutions_per_second":0.02238866403401865,"step_position":549},"timestamp":{"system_time_us":839228589}}
{"global_pose":{"position":{"x":1.4307962109326182,"y":-0.02058724492878894,"z":0.0},"rotation":{"w":0.9931463776647029,"x":0.0,"y":0.0,"z":-0.11687762384837552}},"ir_pose":{"position":{"x":1.528064145783826,"y":-0.043802562679803314,"z":0.0},"rotation":{"w":0.6196155944510511,"x":0.0,"y":0.0,"z":-0.7849055196331081}},"left_encoder_data_input":{"revolutions_per_second":0.02238866403401865,"step_position":587},"line_following_statistics":{"average_speed":0.02238866403401865,"time_spent_on_line":0.351138,"tracking_error":0.0},"right_encoder_data_input":{"revolutions_per_second":0.02238866403401865,"step_position":549},"timestamp":{"system_time_us":839238589}}
{"global_pose":{"position":{"x":1.430809897924565,"y":-0.02059051165659176,"z":0.0},"rotation":{"w":0.9931463776647029,"x":0.0,"y":0.0,"z":-0.11687762384837552}},"ir_pose":{"position":{"x":1.5280778327757727,"y":-0.043805829407606134,"z":0.0},"rotation":{"w":0.6196155944510511,"x":0.0,"y":0.0,"z":-0.7849055196331081}},"left_encoder_data_input":{"revolutions_per_second":0.02238866403401865,"step_position":587},"line_following_statistics":{"average_speed":0.02238866403401865,"time_spent_on_line":0.351138,"tracking_error":0.0},"right_encoder_data_input":{"revolutions_per_second":0.02238866403401865,"step_position":549},"timestamp":{"system_time_us":839248588}}
{"global_pose":{"position":{"x":1.430823557550738,"y":-0.020593771852898346,"z":0.0},"rotation":{"w":0.9931463776647029,"x":0.0,"y":0.0,"z":-0.11687762384837552}},"ir_pose":{"position":{"x":1.5280914924019458,"y":-0.04380908960391272,"z":0.0},"rotation":{"w":0.6196155944510511,"x":0.0,"y":0.0,"z":-0.7849055196331081}},"left_encoder_data_input":{"revolutions_per_second":0.02238866403401865,"step_position":587},"line_following_statistics":{"average_speed":0.02238866403401865,"time_spent_on_line":0.351138,"tracking_error":0.0},"right_encoder_data_input":{"revolutions_per_second":0.02238866403401865,"step_position":549},"timestamp":{"system_time_us":839258593}}
{"global_pose":{"position":{"x":1.4308374087373297,"y":-0.02059707776967823,"z":0.0},"rotation":{"w":0.9931463776647029,"x":0.0,"y":0.0,"z":-0.11687762384837552}},"ir_pose":{"position":{"x":1.5281053435885374,"y":-0.043812395520692604,"z":0.0},"rotation":{"w":0.6196155944510511,"x":0.0,"y":0.0,"z":-0.7849055196331081}},"left_encoder_data_input":{"revolutions_per_second":0.02238866403401865,"step_position":587},"line_following_statistics":{"average_speed":0.02238866403401865,"time_spent_on_line":0.351138,"tracking_error":0.0},"right_encoder_data_input":{"revolutions_per_second":0.02238866403401865,"step_position":549},"timestamp":{"system_time_us":839268594}}
{"global_pose":{"position":{"x":1.4308509233248992,"y":-0.02060030334905516,"z":0.0},"rotation":{"w":0.9931463776647029,"x":0.0,"y":0.0,"z":-0.11687762384837552}},"ir_pose":{"position":{"x":1.528118858176107,"y":-0.043815621100069535,"z":0.0},"rotation":{"w":0.6196155944510511,"x":0.0,"y":0.0,"z":-0.7849055196331081}},"left_encoder_data_input":{"revolutions_per_second":0.02238866403401865,"step_position":587},"line_following_statistics":{"average_speed":0.02238866403401865,"time_spent_on_line":0.351138,"tracking_error":0.0},"right_encoder_data_input":{"revolutions_per_second":0.02238866403401865,"step_position":549},"timestamp":{"system_time_us":839278594}}
{"global_pose":{"position":{"x":1.430865373821945,"y":-0.020603752305600853,"z":0.0},"rotation":{"w":0.9931463776647029,"x":0.0,"y":0.0,"z":-0.11687762384837552}},"ir_pose":{"position":{"x":1.5281333086731528,"y":-0.04381907005661523,"z":0.0},"rotation":{"w":0.6196155944510511,"x":0.0,"y":0.0,"z":-0.7849055196331081}},"left_encoder_data_input":{"revolutions_per_second":0.02238866403401865,"step_position":587},"line_following_statistics":{"average_speed":0.02238866403401865,"time_spent_on_line":0.351138,"tracking_error":0.0},"right_encoder_data_input":{"revolutions_per_second":0.02238866403401865,"step_position":549},"timestamp":{"system_time_us":839288597}}
{"global_pose":{"position":{"x":1.4308783178331235,"y":-0.020606841703282974,"z":0.0},"rotation":{"w":0.9931463776647029,"x":0.0,"y":0.0,"z":-0.11687762384837552}},"ir_pose":{"position":{"x":1.5281462526843312,"y":-0.04382215945429735,"z":0.0},"rotation":{"w":0.6196155944510511,"x":0.0,"y":0.0,"z":-0.7849055196331081}},"left_encoder_data_input":{"revolutions_per_second":0.02238866403401865,"step_position":587},"line_following_statistics":{"average_speed":0.02238866403401865,"time_spent_on_line":0.351138,"tracking_error":0.0},"right_encoder_data_input":{"revolutions_per_second":0.02238866403401865,"step_position":549},"timestamp":{"system_time_us":839298596}}
{"global_pose":{"position":{"x":1.4308919719861413,"y":-0.02061010059329027,"z":0.0},"rotation":{"w":0.9931463776647029,"x":0.0,"y":0.0,"z":-0.11687762384837552}},"ir_pose":{"position":{"x":1.528159906837349,"y":-0.043825418344304645,"z":0.0},"rotation":{"w":0.6196155944510511,"x":0.0,"y":0.0,"z":-0.7849055196331081}},"left_encoder_data_input":{"revolutions_per_second":0.02238866403401865,"step_position":587},"line_following_statistics":{"average_speed":0.02238866403401865,"time_spent_on_line":0.351138,"tracking_error":0.0},"right_encoder_data_input":{"revolutions_per_second":0.02238866403401865,"step_position":549},"timestamp":{"system_time_us":839308598}}
{"global_pose":{"position":{"x":1.4309056767658415,"y":-0.02061337156656573,"z":0.0},"rotation":{"w":0.9931463776647029,"x":0.0,"y":0.0,"z":-0.11687762384837552}},"ir_pose":{"position":{"x":1.5281736116170492,"y":-0.043828689317580105,"z":0.0},"rotation":{"w":0.6196155944510511,"x":0.0,"y":0.0,"z":-0.7849055196331081}},"left_encoder_data_input":{"revolutions_per_second":0.02238866403401865,"step_position":587},"line_following_statistics":{"average_speed":0.02238866403401865,"time_spent_on_line":0.351138,"tracking_error":0.0},"right_encoder_data_input":{"revolutions_per_second":0.02238866403401865,"step_position":549},"timestamp":{"system_time_us":839318598}}
{"global_pose":{"position":{"x":1.4309193446017463,"y":-0.020616633722321254,"z":0.0},"rotation":{"w":0.9931463776647029,"x":0.0,"y":0.0,"z":-0.11687762384837552}},"ir_pose":{"position":{"x":1.528187279452954,"y":-0.04383195147333563,"z":0.0},"rotation":{"w":0.6196155944510511,"x":0.0,"y":0.0,"z":-0.7849055196331081}},"left_encoder_data_input":{"revolutions_per_second":0.02238866403401865,"step_position":587},"line_following_statistics":{"average_speed":0.02238866403401865,"time_spent_on_line":0.351138,"tracking_error":0.0},"right_encoder_data_input":{"revolutions_per_second":0.02238866403401865,"step_position":549},"timestamp":{"system_time_us":839328600}}
{"global_pose":{"position":{"x":1.4309331301104802,"y":-0.0206199239635102,"z":0.0},"rotation":{"w":0.9931463776647029,"x":0.0,"y":0.0,"z":-0.11687762384837552}},"ir_pose":{"position":{"x":1.528201064961688,"y":-0.043835241714524575,"z":0.0},"rotation":{"w":0.6196155944510511,"x":0.0,"y":0.0,"z":-0.7849055196331081}},"left_encoder_data_input":{"revolutions_per_second":0.02238866403401865,"step_position":587},"line_following_statistics":{"average_speed":0.02238866403401865,"time_spent_on_line":0.351138,"tracking_error":0.0},"right_encoder_data_input":{"revolutions_per_second":0.02238866403401865,"step_position":549},"timestamp":{"system_time_us":839338599}}
{"global_pose":{"position":{"x":1.4309467281636608,"y":-0.020623169463950486,"z":0.0},"rotation":{"w":0.9931463776647029,"x":0.0,"y":0.0,"z":-0.11687762384837552}},"ir_pose":{"position":{"x":1.5282146630148685,"y":-0.04383848721496486,"z":0.0},"rotation":{"w":0.6196155944510511,"x":0.0,"y":0.0,"z":-0.7849055196331081}},"left_encoder_data_input":{"revolutions_per_second":0.02238866403401865,"step_position":587},"line_following_statistics":{"average_speed":0.02238866403401865,"time_spent_on_line":0.351138,"tracking_error":0.0},"right_encoder_data_input":{"revolutions_per_second":0.02238866403401865,"step_position":549},"timestamp":{"system_time_us":839348602}}
{"global_pose":{"position":{"x":1.430960442521382,"y":-0.020626442723249427,"z":0.0},"rotation":{"w":0.9931463776647029,"x":0.0,"y":0.0,"z":-0.11687762384837552}},"ir_pose":{"position":{"x":1.5282283773725898,"y":-0.0438417604742638,"z":0.0},"rotation":{"w":0.6196155944510511,"x":0.0,"y":0.0,"z":-0.7849055196331081}},"left_encoder_data_input":{"revolutions_per_second":0.02238866403401865,"step_position":587},"line_following_statistics":{"average_speed":0.02238866403401865,"time_spent_on_line":0.351138,"tracking_error":0.0},"right_encoder_data_input":{"revolutions_per_second":0.02238866403401865,"step_position":549},"timestamp":{"system_time_us":839358602}}
{"global_pose":{"position":{"x":1.430974033733119,"y":-0.020629686590815877,"z":0.0},"rotation":{"w":0.9931463776647029,"x":0.0,"y":0.0,"z":-0.11687762384837552}},"ir_pose":{"position":{"x":1.5282419685843267,"y":-0.04384500434183025,"z":0.0},"rotation":{"w":0.6196155944510511,"x":0.0,"y":0.0,"z":-0.7849055196331081}},"left_encoder_data_input":{"revolutions_per_second":0.02238866403401865,"step_position":587},"line_following_statistics":{"average_speed":0.02238866403401865,"time_spent_on_line":0.351138,"tracking_error":0.0},"right_encoder_data_input":{"revolutions_per_second":0.02238866403401865,"step_position":549},"timestamp":{"system_time_us":839368604}}
{"global_pose":{"position":{"x":1.430987869868535,"y":-0.020632988915272654,"z":0.0},"rotation":{"w":0.9931463776647029,"x":0.0,"y":0.0,"z":-0.11687762384837552}},"ir_pose":{"position":{"x":1.5282558047197428,"y":-0.04384830666628703,"z":0.0},"rotation":{"w":0.6196155944510511,"x":0.0,"y":0.0,"z":-0.7849055196331081}},"left_encoder_data_input":{"revolutions_per_second":0.02238866403401865,"step_position":587},"line_following_statistics":{"average_speed":0.02238866403401865,"time_spent_on_line":0.351138,"tracking_error":0.0},"right_encoder_data_input":{"revolutions_per_second":0.02238866403401865,"step_position":549},"timestamp":{"system_time_us":839378604}}
{"global_pose":{"position":{"x":1.431001551387327,"y":-0.020636254336776294,"z":0.0},"rotation":{"w":0.9931463776647029,"x":0.0,"y":0.0,"z":-0.11687762384837552}},"ir_pose":{"position":{"x":1.5282694862385349,"y":-0.04385157208779067,"z":0.0},"rotation":{"w":0.6196155944510511,"x":0.0,"y":0.0,"z":-0.7849055196331081}},"left_encoder_data_input":{"revolutions_per_second":0.02238866403401865,"step_position":587},"line_following_statistics":{"average_speed":0.02238866403401865,"time_spent_on_line":0.351138,"tracking_error":0.0},"right_encoder_data_input":{"revolutions_per_second":0.02238866403401865,"step_position":549},"timestamp":{"system_time_us":839388602}}
{"global_pose":{"position":{"x":1.431015176806282,"y":-0.020639506368712812,"z":0.0},"rotation":{"w":0.9931463776647029,"x":0.0,"y":0.0,"z":-0.11687762384837552}},"ir_pose":{"position":{"x":1.5282831116574898,"y":-0.04385482411972719,"z":0.0},"rotation":{"w":0.6196155944510511,"x":0.0,"y":0.0,"z":-0.7849055196331081}},"left_encoder_data_input":{"revolutions_per_second":0.02238866403401865,"step_position":587},"line_following_statistics":{"average_speed":0.02238866403401865,"time_spent_on_line":0.351138,"tracking_error":0.0},"right_encoder_data_input":{"revolutions_per_second":0.02238866403401865,"step_position":549},"timestamp":{"system_time_us":839398608}}
{"global_pose":{"position":{"x":1.4310288405373208,"y":-0.020642767544743812,"z":0.0},"rotation":{"w":0.9931463776647029,"x":0.0,"y":0.0,"z":-0.11687762384837552}},"ir_pose":{"position":{"x":1.5282967753885286,"y":-0.04385808529575819,"z":0.0},"rotation":{"w":0.6196155944510511,"x":0.0,"y":0.0,"z":-0.7849055196331081}},"left_encoder_data_input":{"revolutions_per_second":0.02238866403401865,"step_position":587},"line_following_statistics":{"average_speed":0.02238866403401865,"time_spent_on_line":0.351138,"tracking_error":0.0},"right_encoder_data_input":{"revolutions_per_second":0.02238866403401865,"step_position":550},"timestamp":{"system_time_us":839408607}}
{"global_pose":{"position":{"x":1.4310425644730627,"y":-0.020646043090066457,"z":0.0},"rotation":{"w":0.9931463776647029,"x":0.0,"y":0.0,"z":-0.11687762384837552}},"ir_pose":{"position":{"x":1.5283104993242704,"y":-0.04386136084108083,"z":0.0},"rotation":{"w":0.6196155944510511,"x":0.0,"y":0.0,"z":-0.7849055196331081}},"left_encoder_data_input":{"revolutions_per_second":0.02238866403401865,"step_position":587},"line_following_statistics":{"average_speed":0.02238866403401865,"time_spent_on_line":0.351138,"tracking_error":0.0},"right_encoder_data_input":{"revolutions_per_second":0.02238866403401865,"step_position":550},"timestamp":{"system_time_us":839418609}}
{"global_pose":{"position":{"x":1.4310562186260807,"y":-0.020649301980073864,"z":0.0},"rotation":{"w":0.9931463776647029,"x":0.0,"y":0.0,"z":-0.11687762384837552}},"ir_pose":{"position":{"x":1.5283241534772884,"y":-0.04386461973108824,"z":0.0},"rotation":{"w":0.6196155944510511,"x":0.0,"y":0.0,"z":-0.7849055196331081}},"left_encoder_data_input":{"revolutions_per_second":0.02238866403401865,"step_position":587},"line_following_statistics":{"average_speed":0.02238866403401865,"time_spent_on_line":0.351138,"tracking_error":0.0},"right_encoder_data_input":{"revolutions_per_second":0.02238866403401865,"step_position":550},"timestamp":{"system_time_us":839428608}}
{"global_pose":{"position":{"x":1.431069916564337,"y":-0.020652571320475266,"z":0.0},"rotation":{"w":0.9931463776647029,"x":0.0,"y":0.0,"z":-0.11687762384837552}},"ir_pose":{"position":{"x":1.5283378514155448,"y":-0.04386788907148964,"z":0.0},"rotation":{"w":0.6196155944510511,"x":0.0,"y":0.0,"z":-0.7849055196331081}},"left_encoder_data_input":{"revolutions_per_second":0.02238866403401865,"step_position":587},"line_following_statistics":{"average_speed":0.02238866403401865,"time_spent_on_line":0.351138,"tracking_error":0.0},"right_encoder_data_input":{"revolutions_per_second":0.02238866403401865,"step_position":550},"timestamp":{"system_time_us":839438607}}
{"global_pose":{"position":{"x":1.4310835625076228,"y":-0.020655828251033848,"z":0.0},"rotation":{"w":0.9931463776647029,"x":0.0,"y":0.0,"z":-0.11687762384837552}},"ir_pose":{"position":{"x":1.5283514973588306,"y":-0.04387114600204822,"z":0.0},"rotation":{"w":0.6196155944510511,"x":0.0,"y":0.0,"z":-0.7849055196331081}},"left_encoder_data_input":{"revolutions_per_second":0.02238866403401865,"step_position":587},"line_following_statistics":{"average_speed":0.02238866403401865,"time_spent_on_line":0.351138,"tracking_error":0.0},"right_encoder_data_input":{"revolutions_per_second":0.02238866403401865,"step_position":550},"timestamp":{"system_time_us":839448608}}
{"global_pose":{"position":{"x":1.4310972700239,"y":-0.02065909987745873,"z":0.0},"rotation":{"w":0.9931463776647029,"x":0.0,"y":0.0,"z":-0.11687762384837552}},"ir_pose":{"position":{"x":1.5283652048751077,"y":-0.043874417628473106,"z":0.0},"rotation":{"w":0.6196155944510511,"x":0.0,"y":0.0,"z":-0.7849055196331081}},"left_encoder_data_input":{"revolutions_per_second":0.02238866403401865,"step_position":587},"line_following_statistics":{"average_speed":0.02238866403401865,"time_spent_on_line":0.351138,"tracking_error":0.0},"right_encoder_data_input":{"revolutions_per_second":0.02238866403401865,"step_position":550},"timestamp":{"system_time_us":839458609}}
{"global_pose":{"position":{"x":1.4311110008010857,"y":-0.020662377055655323,"z":0.0},"rotation":{"w":0.9931463776647029,"x":0.0,"y":0.0,"z":-0.11687762384837552}},"ir_pose":{"position":{"x":1.5283789356522934,"y":-0.0438776948066697,"z":0.0},"rotation":{"w":0.6196155944510511,"x":0.0,"y":0.0,"z":-0.7849055196331081}},"left_encoder_data_input":{"revolutions_per_second":0.02238866403401865,"step_position":587},"line_following_statistics":{"average_speed":0.02238866403401865,"time_spent_on_line":0.351138,"tracking_error":0.0},"right_encoder_data_input":{"revolutions_per_second":0.02238866403401865,"step_position":550},"timestamp":{"system_time_us":839468613}}
{"global_pose":{"position":{"x":1.4311246275883294,"y":-0.02066562941416661,"z":0.0},"rotation":{"w":0.9931463776647029,"x":0.0,"y":0.0,"z":-0.11687762384837552}},"ir_pose":{"position":{"x":1.5283925624395371,"y":-0.043880947165180983,"z":0.0},"rotation":{"w":0.6196155944510511,"x":0.0,"y":0.0,"z":-0.7849055196331081}},"left_encoder_data_input":{"revolutions_per_second":0.02238866403401865,"step_position":587},"line_following_statistics":{"average_speed":0.02238866403401865,"time_spent_on_line":0.351138,"tracking_error":0.0},"right_encoder_data_input":{"revolutions_per_second":0.02238866403401865,"step_position":550},"timestamp":{"system_time_us":839478613}}
{"global_pose":{"position":{"x":1.4311383050022553,"y":-0.020668893855945836,"z":0.0},"rotation":{"w":0.9931463776647029,"x":0.0,"y":0.0,"z":-0.11687762384837552}},"ir_pose":{"position":{"x":1.528406239853463,"y":-0.04388421160696021,"z":0.0},"rotation":{"w":0.6196155944510511,"x":0.0,"y":0.0,"z":-0.7849055196331081}},"left_encoder_data_input":{"revolutions_per_second":0.02238866403401865,"step_position":587},"line_following_statistics":{"average_speed":0.02238866403401865,"time_spent_on_line":0.351138,"tracking_error":0.0},"right_encoder_data_input":{"revolutions_per_second":0.02238866403401865,"step_position":550},"timestamp":{"system_time_us":839488615}}
{"global_pose":{"position":{"x":1.4311520138868215,"y":-0.020672165808945597,"z":0.0},"rotation":{"w":0.9931463776647029,"x":0.0,"y":0.0,"z":-0.11687762384837552}},"ir_pose":{"position":{"x":1.5284199487380292,"y":-0.04388748355995997,"z":0.0},"rotation":{"w":0.6196155944510511,"x":0.0,"y":0.0,"z":-0.7849055196331081}},"left_encoder_data_input":{"revolutions_per_second":0.02238866403401865,"step_position":587},"line_following_statistics":{"average_speed":0.02238866403401865,"time_spent_on_line":0.351138,"tracking_error":0.0},"right_encoder_data_input":{"revolutions_per_second":0.02238866403401865,"step_position":550},"timestamp":{"system_time_us":839498616}}
{"global_pose":{"position":{"x":1.4311656899324585,"y":-0.020675429924149835,"z":0.0},"rotation":{"w":0.9931463776647029,"x":0.0,"y":0.0,"z":-0.11687762384837552}},"ir_pose":{"position":{"x":1.5284336247836663,"y":-0.04389074767516421,"z":0.0},"rotation":{"w":0.6196155944510511,"x":0.0,"y":0.0,"z":-0.7849055196331081}},"left_encoder_data_input":{"revolutions_per_second":0.02238866403401865,"step_position":587},"line_following_statistics":{"average_speed":0.02238866403401865,"time_spent_on_line":0.351138,"tracking_error":0.0},"right_encoder_data_input":{"revolutions_per_second":0.02238866403401865,"step_position":550},"timestamp":{"system_time_us":839508616}}
{"global_pose":{"position":{"x":1.431179305773393,"y":-0.02067867967006276,"z":0.0},"rotation":{"w":0.9931463776647029,"x":0.0,"y":0.0,"z":-0.11687762384837552}},"ir_pose":{"position":{"x":1.5284472406246008,"y":-0.043893997421077136,"z":0.0},"rotation":{"w":0.6196155944510511,"x":0.0,"y":0.0,"z":-0.7849055196331081}},"left_encoder_data_input":{"revolutions_per_second":0.02238866403401865,"step_position":587},"line_following_statistics":{"average_speed":0.02238866403401865,"time_spent_on_line":0.351138,"tracking_error":0.0},"right_encoder_data_input":{"revolutions_per_second":0.02238866403401865,"step_position":550},"timestamp":{"system_time_us":839518619}}
{"global_pose":{"position":{"x":1.4311930310774235,"y":-0.020681955541960173,"z":0.0},"rotation":{"w":0.9931463776647029,"x":0.0,"y":0.0,"z":-0.11687762384837552}},"ir_pose":{"position":{"x":1.5284609659286312,"y":-0.04389727329297455,"z":0.0},"rotation":{"w":0.6196155944510511,"x":0.0,"y":0.0,"z":-0.7849055196331081}},"left_encoder_data_input":{"revolutions_per_second":0.02238866403401865,"step_position":587},"line_following_statistics":{"average_speed":0.02238866403401865,"time_spent_on_line":0.351138,"tracking_error":0.0},"right_encoder_data_input":{"revolutions_per_second":0.02238866403401865,"step_position":550},"timestamp":{"system_time_us":839528619}}
{"global_pose":{"position":{"x":1.4312067262791026,"y":-0.020685224229211818,"z":0.0},"rotation":{"w":0.9931463776647029,"x":0.0,"y":0.0,"z":-0.11687762384837552}},"ir_pose":{"position":{"x":1.5284746611303104,"y":-0.04390054198022619,"z":0.0},"rotation":{"w":0.6196155944510511,"x":0.0,"y":0.0,"z":-0.7849055196331081}},"left_encoder_data_input":{"revolutions_per_second":0.02238866403401865,"step_position":587},"line_following_statistics":{"average_speed":0.02238866403401865,"time_spent_on_line":0.351138,"tracking_error":0.0},"right_encoder_data_input":{"revolutions_per_second":0.02238866403401865,"step_position":550},"timestamp":{"system_time_us":839538620}}
{"global_pose":{"position":{"x":1.4312205596779413,"y":-0.020688525900519172,"z":0.0},"rotation":{"w":0.9931463776647029,"x":0.0,"y":0.0,"z":-0.11687762384837552}},"ir_pose":{"position":{"x":1.528488494529149,"y":-0.04390384365153355,"z":0.0},"rotation":{"w":0.6196155944510511,"x":0.0,"y":0.0,"z":-0.7849055196331081}},"left_encoder_data_input":{"revolutions_per_second":0.02238866403401865,"step_position":587},"line_following_statistics":{"average_speed":0.02238866403401865,"time_spent_on_line":0.351138,"tracking_error":0.0},"right_encoder_data_input":{"revolutions_per_second":0.02238866403401865,"step_position":550},"timestamp":{"system_time_us":839548621}}
{"global_pose":{"position":{"x":1.4312341071044394,"y":-0.020691759317691516,"z":0.0},"rotation":{"w":0.9931463776647029,"x":0.0,"y":0.0,"z":-0.11687762384837552}},"ir_pose":{"position":{"x":1.5285020419556472,"y":-0.04390707706870589,"z":0.0},"rotation":{"w":0.6196155944510511,"x":0.0,"y":0.0,"z":-0.7849055196331081}},"left_encoder_data_input":{"revolutions_per_second":0.02238866403401865,"step_position":587},"line_following_statistics":{"average_speed":0.02238866403401865,"time_spent_on_line":0.351138,"tracking_error":0.0},"right_encoder_data_input":{"revolutions_per_second":0.02238866403401865,"step_position":550},"timestamp":{"system_time_us":839558621}}
{"global_pose":{"position":{"x":1.4312477804134995,"y":-0.02069502277974633,"z":0.0},"rotation":{"w":0.9931463776647029,"x":0.0,"y":0.0,"z":-0.11687762384837552}},"ir_pose":{"position":{"x":1.5285157152647073,"y":-0.043910340530760705,"z":0.0},"rotation":{"w":0.6196155944510511,"x":0.0,"y":0.0,"z":-0.7849055196331081}},"left_encoder_data_input":{"revolutions_per_second":0.02238866403401865,"step_position":587},"line_following_statistics":{"average_speed":0.02238866403401865,"time_spent_on_line":0.351138,"tracking_error":0.0},"right_encoder_data_input":{"revolutions_per_second":0.02238866403401865,"step_position":550},"timestamp":{"system_time_us":839568620}}
{"global_pose":{"position":{"x":1.4312614304616513,"y":-0.020698280690029325,"z":0.0},"rotation":{"w":0.9931463776647029,"x":0.0,"y":0.0,"z":-0.11687762384837552}},"ir_pose":{"position":{"x":1.528529365312859,"y":-0.0439135984410437,"z":0.0},"rotation":{"w":0.6196155944510511,"x":0.0,"y":0.0,"z":-0.7849055196331081}},"left_encoder_data_input":{"revolutions_per_second":0.02238866403401865,"step_position":587},"line_following_statistics":{"average_speed":0.02238866403401865,"time_spent_on_line":0.351138,"tracking_error":0.0},"right_encoder_data_input":{"revolutions_per_second":0.02238866403401865,"step_position":550},"timestamp":{"system_time_us":839578625}}
{"global_pose":{"position":{"x":1.4312751489242386,"y":-0.02070155492905268,"z":0.0},"rotation":{"w":0.9931463776647029,"x":0.0,"y":0.0,"z":-0.11687762384837552}},"ir_pose":{"position":{"x":1.5285430837754463,"y":-0.043916872680067054,"z":0.0},"rotation":{"w":0.6196155944510511,"x":0.0,"y":0.0,"z":-0.7849055196331081}},"left_encoder_data_input":{"revolutions_per_second":0.02238866403401865,"step_position":587},"line_following_statistics":{"average_speed":0.02238866403401865,"time_spent_on_line":0.351138,"tracking_error":0.0},"right_encoder_data_input":{"revolutions_per_second":0.02238866403401865,"step_position":550},"timestamp":{"system_time_us":839588624}}
{"global_pose":{"position":{"x":1.4312888974891775,"y":-0.02070483635272191,"z":0.0},"rotation":{"w":0.9931463776647029,"x":0.0,"y":0.0,"z":-0.11687762384837552}},"ir_pose":{"position":{"x":1.5285568323403853,"y":-0.043920154103736286,"z":0.0},"rotation":{"w":0.6196155944510511,"x":0.0,"y":0.0,"z":-0.7849055196331081}},"left_encoder_data_input":{"revolutions_per_second":0.02238866403401865,"step_position":587},"line_following_statistics":{"average_speed":0.02238866403401865,"time_spent_on_line":0.351138,"tracking_error":0.0},"right_encoder_data_input":{"revolutions_per_second":0.02238866403401865,"step_position":550},"timestamp":{"system_time_us":839598627}}
{"global_pose":{"position":{"x":1.4313025365910192,"y":-0.020708091650406435,"z":0.0},"rotation":{"w":0.9931463776647029,"x":0.0,"y":0.0,"z":-0.11687762384837552}},"ir_pose":{"position":{"x":1.528570471442227,"y":-0.04392340940142081,"z":0.0},"rotation":{"w":0.6196155944510511,"x":0.0,"y":0.0,"z":-0.7849055196331081}},"left_encoder_data_input":{"revolutions_per_second":0.02238866403401865,"step_position":587},"line_following_statistics":{"average_speed":0.02238866403401865,"time_spent_on_line":0.351138,"tracking_error":0.0},"right_encoder_data_input":{"revolutions_per_second":0.02238866403401865,"step_position":550},"timestamp":{"system_time_us":839608627}}
{"global_pose":{"position":{"x":1.4313162085317905,"y":-0.02071135478588637,"z":0.0},"rotation":{"w":0.9931463776647029,"x":0.0,"y":0.0,"z":-0.11687762384837552}},"ir_pose":{"position":{"x":1.5285841433829983,"y":-0.043926672536900746,"z":0.0},"rotation":{"w":0.6196155944510511,"x":0.0,"y":0.0,"z":-0.7849055196331081}},"left_encoder_data_input":{"revolutions_per_second":0.02238866403401865,"step_position":587},"line_following_statistics":{"average_speed":0.02238866403401865,"time_spent_on_line":0.351138,"tracking_error":0.0},"right_encoder_data_input":{"revolutions_per_second":0.02238866403401865,"step_position":550},"timestamp":{"system_time_us":839618628}}
{"global_pose":{"position":{"x":1.4313299871990808,"y":-0.02071464339420137,"z":0.0},"rotation":{"w":0.9931463776647029,"x":0.0,"y":0.0,"z":-0.11687762384837552}},"ir_pose":{"position":{"x":1.5285979220502885,"y":-0.043929961145215746,"z":0.0},"rotation":{"w":0.6196155944510511,"x":0.0,"y":0.0,"z":-0.7849055196331081}},"left_encoder_data_input":{"revolutions_per_second":0.02238866403401865,"step_position":587},"line_following_statistics":{"average_speed":0.02238866403401865,"time_spent_on_line":0.351138,"tracking_error":0.0},"right_encoder_data_input":{"revolutions_per_second":0.02238866403401865,"step_position":550},"timestamp":{"system_time_us":839628628}}
{"global_pose":{"position":{"x":1.4313436085131697,"y":-0.020717894446413476,"z":0.0},"rotation":{"w":0.9931463776647029,"x":0.0,"y":0.0,"z":-0.11687762384837552}},"ir_pose":{"position":{"x":1.5286115433643774,"y":-0.04393321219742785,"z":0.0},"rotation":{"w":0.6196155944510511,"x":0.0,"y":0.0,"z":-0.7849055196331081}},"left_encoder_data_input":{"revolutions_per_second":0.02238866403401865,"step_position":587},"line_following_statistics":{"average_speed":0.02238866403401865,"time_spent_on_line":0.351138,"tracking_error":0.0},"right_encoder_data_input":{"revolutions_per_second":0.02238866403401865,"step_position":550},"timestamp":{"system_time_us":839638632}}
{"global_pose":{"position":{"x":1.4313573912853261,"y":-0.020721184034452778,"z":0.0},"rotation":{"w":0.9931463776647029,"x":0.0,"y":0.0,"z":-0.11687762384837552}},"ir_pose":{"position":{"x":1.528625326136534,"y":-0.04393650178546715,"z":0.0},"rotation":{"w":0.6196155944510511,"x":0.0,"y":0.0,"z":-0.7849055196331081}},"left_encoder_data_input":{"revolutions_per_second":0.02238866403401865,"step_position":587},"line_following_statistics":{"average_speed":0.02238866403401865,"time_spent_on_line":0.351138,"tracking_error":0.0},"right_encoder_data_input":{"revolutions_per_second":0.02238866403401865,"step_position":550},"timestamp":{"system_time_us":839648630}}
{"global_pose":{"position":{"x":1.4313709168192055,"y":-0.02072441222642829,"z":0.0},"rotation":{"w":0.9931463776647029,"x":0.0,"y":0.0,"z":-0.11687762384837552}},"ir_pose":{"position":{"x":1.5286388516704132,"y":-0.043939729977442665,"z":0.0},"rotation":{"w":0.6196155944510511,"x":0.0,"y":0.0,"z":-0.7849055196331081}},"left_encoder_data_input":{"revolutions_per_second":0.02238866403401865,"step_position":587},"line_following_statistics":{"average_speed":0.02238866403401865,"time_spent_on_line":0.351138,"tracking_error":0.0},"right_encoder_data_input":{"revolutions_per_second":0.02238866403401865,"step_position":550},"timestamp":{"system_time_us":839658632}}
